{
"meta":{"test_sets":[],"test_metrics":[],"learn_metrics":[{"best_value":"Min","name":"RMSE"}],"launch_mode":"Train","parameters":"","iteration_count":1000,"learn_sets":["learn"],"name":"experiment"},
"iterations":[
{"learn":[14.82257015],"iteration":0,"passed_time":0.1321855693,"remaining_time":132.0533838},
{"learn":[14.46070487],"iteration":1,"passed_time":0.1336305548,"remaining_time":66.68164686},
{"learn":[14.0832535],"iteration":2,"passed_time":0.1348945005,"remaining_time":44.82993901},
{"learn":[13.73489377],"iteration":3,"passed_time":0.1361776168,"remaining_time":33.90822659},
{"learn":[13.37028771],"iteration":4,"passed_time":0.137356821,"remaining_time":27.33400737},
{"learn":[13.0624361],"iteration":5,"passed_time":0.1385749113,"remaining_time":22.95724363},
{"learn":[12.75526534],"iteration":6,"passed_time":0.1396390981,"remaining_time":19.80880349},
{"learn":[12.48631396],"iteration":7,"passed_time":0.1410962745,"remaining_time":17.49593804},
{"learn":[12.1735564],"iteration":8,"passed_time":0.1423480894,"remaining_time":15.67410629},
{"learn":[11.87175727],"iteration":9,"passed_time":0.1435719974,"remaining_time":14.21362774},
{"learn":[11.57782349],"iteration":10,"passed_time":0.1450753849,"remaining_time":13.04359597},
{"learn":[11.33593004],"iteration":11,"passed_time":0.146586793,"remaining_time":12.06897929},
{"learn":[11.11941014],"iteration":12,"passed_time":0.1481600328,"remaining_time":11.24876557},
{"learn":[10.87323163],"iteration":13,"passed_time":0.1494143009,"remaining_time":10.52303577},
{"learn":[10.63194486],"iteration":14,"passed_time":0.1509293438,"remaining_time":9.911026912},
{"learn":[10.39687818],"iteration":15,"passed_time":0.1528915278,"remaining_time":9.402828962},
{"learn":[10.16985436],"iteration":16,"passed_time":0.15427745,"remaining_time":8.920866669},
{"learn":[9.962407662],"iteration":17,"passed_time":0.1558807596,"remaining_time":8.504161441},
{"learn":[9.751365073],"iteration":18,"passed_time":0.1573514138,"remaining_time":8.124301944},
{"learn":[9.551640413],"iteration":19,"passed_time":0.1591596443,"remaining_time":7.79882257},
{"learn":[9.378819955],"iteration":20,"passed_time":0.1604403564,"remaining_time":7.479576617},
{"learn":[9.20225973],"iteration":21,"passed_time":0.1619511647,"remaining_time":7.199465412},
{"learn":[9.019534302],"iteration":22,"passed_time":0.1631956899,"remaining_time":6.93226909},
{"learn":[8.856515278],"iteration":23,"passed_time":0.1645373283,"remaining_time":6.691184686},
{"learn":[8.709990645],"iteration":24,"passed_time":0.1660018788,"remaining_time":6.474073272},
{"learn":[8.573452548],"iteration":25,"passed_time":0.1674420226,"remaining_time":6.272635771},
{"learn":[8.424424402],"iteration":26,"passed_time":0.1686869942,"remaining_time":6.078979458},
{"learn":[8.282452905],"iteration":27,"passed_time":0.1699868879,"remaining_time":5.900973394},
{"learn":[8.163074828],"iteration":28,"passed_time":0.171325117,"remaining_time":5.73643754},
{"learn":[8.042261538],"iteration":29,"passed_time":0.1726349987,"remaining_time":5.581864958},
{"learn":[7.917620451],"iteration":30,"passed_time":0.1743686458,"remaining_time":5.450426381},
{"learn":[7.811058167],"iteration":31,"passed_time":0.1758152983,"remaining_time":5.318412774},
{"learn":[7.702905144],"iteration":32,"passed_time":0.176990552,"remaining_time":5.186359508},
{"learn":[7.588448289],"iteration":33,"passed_time":0.1781939829,"remaining_time":5.062805515},
{"learn":[7.483893797],"iteration":34,"passed_time":0.1793647898,"remaining_time":4.94534349},
{"learn":[7.390232126],"iteration":35,"passed_time":0.1804821579,"remaining_time":4.832911117},
{"learn":[7.298881987],"iteration":36,"passed_time":0.1815390551,"remaining_time":4.724921894},
{"learn":[7.218368907],"iteration":37,"passed_time":0.1826581445,"remaining_time":4.624135133},
{"learn":[7.128016208],"iteration":38,"passed_time":0.183866522,"remaining_time":4.530659684},
{"learn":[7.041186653],"iteration":39,"passed_time":0.1849426346,"remaining_time":4.438623231},
{"learn":[6.966710309],"iteration":40,"passed_time":0.1861693964,"remaining_time":4.354547589},
{"learn":[6.892451513],"iteration":41,"passed_time":0.1873055332,"remaining_time":4.272350018},
{"learn":[6.814096541],"iteration":42,"passed_time":0.18854043,"remaining_time":4.196120732},
{"learn":[6.754816575],"iteration":43,"passed_time":0.1897565987,"remaining_time":4.122893372},
{"learn":[6.688185519],"iteration":44,"passed_time":0.1908599674,"remaining_time":4.05047264},
{"learn":[6.628906095],"iteration":45,"passed_time":0.1919864857,"remaining_time":3.981632768},
{"learn":[6.566008972],"iteration":46,"passed_time":0.1931598526,"remaining_time":3.916624245},
{"learn":[6.507201288],"iteration":47,"passed_time":0.1943409692,"remaining_time":3.854429223},
{"learn":[6.449633757],"iteration":48,"passed_time":0.1955888589,"remaining_time":3.796020507},
{"learn":[6.393950148],"iteration":49,"passed_time":0.1967087695,"remaining_time":3.73746662},
{"learn":[6.345517431],"iteration":50,"passed_time":0.1978284196,"remaining_time":3.681160201},
{"learn":[6.296532302],"iteration":51,"passed_time":0.1994376771,"remaining_time":3.635902267},
{"learn":[6.249991247],"iteration":52,"passed_time":0.2011765559,"remaining_time":3.594607517},
{"learn":[6.206006576],"iteration":53,"passed_time":0.2027763208,"remaining_time":3.552340731},
{"learn":[6.166062659],"iteration":54,"passed_time":0.204126891,"remaining_time":3.507271127},
{"learn":[6.122237739],"iteration":55,"passed_time":0.2053073868,"remaining_time":3.46089595},
{"learn":[6.084215025],"iteration":56,"passed_time":0.2064322639,"remaining_time":3.415186401},
{"learn":[6.048875301],"iteration":57,"passed_time":0.2075434577,"remaining_time":3.37079202},
{"learn":[6.007561],"iteration":58,"passed_time":0.2085612031,"remaining_time":3.326374443},
{"learn":[5.975521031],"iteration":59,"passed_time":0.2095484984,"remaining_time":3.282926474},
{"learn":[5.942376628],"iteration":60,"passed_time":0.2106081244,"remaining_time":3.241984079},
{"learn":[5.908228265],"iteration":61,"passed_time":0.2116024089,"remaining_time":3.20133967},
{"learn":[5.874150774],"iteration":62,"passed_time":0.2125303156,"remaining_time":3.160966757},
{"learn":[5.835949408],"iteration":63,"passed_time":0.2136996362,"remaining_time":3.125357179},
{"learn":[5.806083458],"iteration":64,"passed_time":0.2148762068,"remaining_time":3.09091159},
{"learn":[5.779526732],"iteration":65,"passed_time":0.2158617445,"remaining_time":3.054770747},
{"learn":[5.750561398],"iteration":66,"passed_time":0.2168949103,"remaining_time":3.020342557},
{"learn":[5.722913105],"iteration":67,"passed_time":0.2179359218,"remaining_time":2.987004104},
{"learn":[5.704007413],"iteration":68,"passed_time":0.2189796816,"remaining_time":2.954638893},
{"learn":[5.678255332],"iteration":69,"passed_time":0.2200092627,"remaining_time":2.922980205},
{"learn":[5.652712725],"iteration":70,"passed_time":0.2211119352,"remaining_time":2.893140673},
{"learn":[5.629985328],"iteration":71,"passed_time":0.222241128,"remaining_time":2.864441205},
{"learn":[5.61111325],"iteration":72,"passed_time":0.2234252334,"remaining_time":2.837194402},
{"learn":[5.589227561],"iteration":73,"passed_time":0.2245110989,"remaining_time":2.80942267},
{"learn":[5.5680724],"iteration":74,"passed_time":0.2256631572,"remaining_time":2.783178938},
{"learn":[5.551073224],"iteration":75,"passed_time":0.2276648229,"remaining_time":2.767924952},
{"learn":[5.532690284],"iteration":76,"passed_time":0.2291371746,"remaining_time":2.746670288},
{"learn":[5.511040486],"iteration":77,"passed_time":0.2306399312,"remaining_time":2.726282264},
{"learn":[5.494620674],"iteration":78,"passed_time":0.2320025126,"remaining_time":2.704738153},
{"learn":[5.474436789],"iteration":79,"passed_time":0.2333813907,"remaining_time":2.683885993},
{"learn":[5.463497374],"iteration":80,"passed_time":0.2341789651,"remaining_time":2.656919369},
{"learn":[5.446505577],"iteration":81,"passed_time":0.235319643,"remaining_time":2.634432101},
{"learn":[5.43345886],"iteration":82,"passed_time":0.2364263761,"remaining_time":2.61208418},
{"learn":[5.414930176],"iteration":83,"passed_time":0.2376164442,"remaining_time":2.591150748},
{"learn":[5.401617028],"iteration":84,"passed_time":0.2388257028,"remaining_time":2.570888448},
{"learn":[5.387749003],"iteration":85,"passed_time":0.2400738081,"remaining_time":2.5514821},
{"learn":[5.375811344],"iteration":86,"passed_time":0.2414817794,"remaining_time":2.534170857},
{"learn":[5.363087139],"iteration":87,"passed_time":0.2432114861,"remaining_time":2.520555401},
{"learn":[5.351541245],"iteration":88,"passed_time":0.2442163345,"remaining_time":2.499787424},
{"learn":[5.337413296],"iteration":89,"passed_time":0.245278183,"remaining_time":2.480034961},
{"learn":[5.320255487],"iteration":90,"passed_time":0.2463903385,"remaining_time":2.461195799},
{"learn":[5.306219673],"iteration":91,"passed_time":0.2474598624,"remaining_time":2.442321251},
{"learn":[5.295417833],"iteration":92,"passed_time":0.2485118231,"remaining_time":2.423658318},
{"learn":[5.285420218],"iteration":93,"passed_time":0.2495279111,"remaining_time":2.405024335},
{"learn":[5.274932424],"iteration":94,"passed_time":0.2507483398,"remaining_time":2.388707868},
{"learn":[5.267859917],"iteration":95,"passed_time":0.2521752261,"remaining_time":2.374650046},
{"learn":[5.257192025],"iteration":96,"passed_time":0.2533621252,"remaining_time":2.358618547},
{"learn":[5.244387989],"iteration":97,"passed_time":0.2546619936,"remaining_time":2.343929778},
{"learn":[5.237235152],"iteration":98,"passed_time":0.2561209724,"remaining_time":2.330959557},
{"learn":[5.225870002],"iteration":99,"passed_time":0.2574722688,"remaining_time":2.317250419},
{"learn":[5.216887292],"iteration":100,"passed_time":0.2588497146,"remaining_time":2.304018746},
{"learn":[5.210624607],"iteration":101,"passed_time":0.2599949486,"remaining_time":2.288975135},
{"learn":[5.202813277],"iteration":102,"passed_time":0.2611761801,"remaining_time":2.274514889},
{"learn":[5.19316382],"iteration":103,"passed_time":0.2623891589,"remaining_time":2.260583523},
{"learn":[5.185029098],"iteration":104,"passed_time":0.2636945337,"remaining_time":2.247681978},
{"learn":[5.176548883],"iteration":105,"passed_time":0.2647857363,"remaining_time":2.233192908},
{"learn":[5.169024646],"iteration":106,"passed_time":0.265932323,"remaining_time":2.21941649},
{"learn":[5.162145349],"iteration":107,"passed_time":0.2676147972,"remaining_time":2.210299992},
{"learn":[5.156850871],"iteration":108,"passed_time":0.2690625712,"remaining_time":2.199401385},
{"learn":[5.149455556],"iteration":109,"passed_time":0.2704851065,"remaining_time":2.188470408},
{"learn":[5.142204329],"iteration":110,"passed_time":0.2718322427,"remaining_time":2.177106881},
{"learn":[5.137136805],"iteration":111,"passed_time":0.2728727931,"remaining_time":2.163491431},
{"learn":[5.127035173],"iteration":112,"passed_time":0.273953642,"remaining_time":2.150414871},
{"learn":[5.119262277],"iteration":113,"passed_time":0.2750580019,"remaining_time":2.137731489},
{"learn":[5.115736422],"iteration":114,"passed_time":0.2759259393,"remaining_time":2.123430055},
{"learn":[5.107723016],"iteration":115,"passed_time":0.2769126986,"remaining_time":2.110265738},
{"learn":[5.101978294],"iteration":116,"passed_time":0.2780147255,"remaining_time":2.098179509},
{"learn":[5.091766344],"iteration":117,"passed_time":0.2791183745,"remaining_time":2.086291579},
{"learn":[5.084366412],"iteration":118,"passed_time":0.2802478629,"remaining_time":2.074776195},
{"learn":[5.076830195],"iteration":119,"passed_time":0.2814193416,"remaining_time":2.063741838},
{"learn":[5.069173689],"iteration":120,"passed_time":0.2826457429,"remaining_time":2.053269488},
{"learn":[5.062607567],"iteration":121,"passed_time":0.2837207531,"remaining_time":2.04185919},
{"learn":[5.05543113],"iteration":122,"passed_time":0.2847514867,"remaining_time":2.030301251},
{"learn":[5.049369525],"iteration":123,"passed_time":0.2859992062,"remaining_time":2.020446005},
{"learn":[5.041085786],"iteration":124,"passed_time":0.2870564129,"remaining_time":2.00939489},
{"learn":[5.034442606],"iteration":125,"passed_time":0.2881150281,"remaining_time":1.998512179},
{"learn":[5.029600144],"iteration":126,"passed_time":0.2892347436,"remaining_time":1.988204182},
{"learn":[5.02490204],"iteration":127,"passed_time":0.2902487031,"remaining_time":1.97731929},
{"learn":[5.019190389],"iteration":128,"passed_time":0.291219332,"remaining_time":1.966294869},
{"learn":[5.015253595],"iteration":129,"passed_time":0.2922464341,"remaining_time":1.955803059},
{"learn":[5.012481024],"iteration":130,"passed_time":0.2932814733,"remaining_time":1.9455084},
{"learn":[5.006255201],"iteration":131,"passed_time":0.294418857,"remaining_time":1.936027029},
{"learn":[5.001867638],"iteration":132,"passed_time":0.2957800813,"remaining_time":1.928130304},
{"learn":[4.994109199],"iteration":133,"passed_time":0.2970679991,"remaining_time":1.919857368},
{"learn":[4.989335564],"iteration":134,"passed_time":0.2985251355,"remaining_time":1.912772164},
{"learn":[4.987108083],"iteration":135,"passed_time":0.2994881686,"remaining_time":1.902630718},
{"learn":[4.983901494],"iteration":136,"passed_time":0.3007839817,"remaining_time":1.894719534},
{"learn":[4.979366849],"iteration":137,"passed_time":0.301941602,"remaining_time":1.886041021},
{"learn":[4.975637809],"iteration":138,"passed_time":0.3030765725,"remaining_time":1.877330424},
{"learn":[4.973158634],"iteration":139,"passed_time":0.3040877893,"remaining_time":1.867967849},
{"learn":[4.967380491],"iteration":140,"passed_time":0.3053160578,"remaining_time":1.860046054},
{"learn":[4.960746947],"iteration":141,"passed_time":0.3063670825,"remaining_time":1.851147583},
{"learn":[4.959776144],"iteration":142,"passed_time":0.3069436547,"remaining_time":1.839515469},
{"learn":[4.952369567],"iteration":143,"passed_time":0.3081688697,"remaining_time":1.831892726},
{"learn":[4.946129551],"iteration":144,"passed_time":0.3094428687,"remaining_time":1.824645881},
{"learn":[4.942661532],"iteration":145,"passed_time":0.3104497551,"remaining_time":1.81591843},
{"learn":[4.936177472],"iteration":146,"passed_time":0.3115207857,"remaining_time":1.807668233},
{"learn":[4.930240459],"iteration":147,"passed_time":0.3125462414,"remaining_time":1.799252687},
{"learn":[4.925260973],"iteration":148,"passed_time":0.3136368184,"remaining_time":1.791308271},
{"learn":[4.924145356],"iteration":149,"passed_time":0.3143836457,"remaining_time":1.781507325},
{"learn":[4.92030015],"iteration":150,"passed_time":0.3153681019,"remaining_time":1.773162374},
{"learn":[4.916746636],"iteration":151,"passed_time":0.3165448928,"remaining_time":1.765987297},
{"learn":[4.910791579],"iteration":152,"passed_time":0.3175725614,"remaining_time":1.758065095},
{"learn":[4.907355438],"iteration":153,"passed_time":0.3185142864,"remaining_time":1.7497603},
{"learn":[4.903234446],"iteration":154,"passed_time":0.3195605695,"remaining_time":1.742120524},
{"learn":[4.899655789],"iteration":155,"passed_time":0.3205931646,"remaining_time":1.734491224},
{"learn":[4.890694425],"iteration":156,"passed_time":0.3225344057,"remaining_time":1.731824866},
{"learn":[4.883691178],"iteration":157,"passed_time":0.3236287324,"remaining_time":1.724654384},
{"learn":[4.881536148],"iteration":158,"passed_time":0.3250811225,"remaining_time":1.719454239},
{"learn":[4.880303739],"iteration":159,"passed_time":0.3258121937,"remaining_time":1.710514017},
{"learn":[4.872962979],"iteration":160,"passed_time":0.3270209069,"remaining_time":1.70416485},
{"learn":[4.867757541],"iteration":161,"passed_time":0.3283414574,"remaining_time":1.698457662},
{"learn":[4.865514092],"iteration":162,"passed_time":0.3293926523,"remaining_time":1.691421166},
{"learn":[4.861483981],"iteration":163,"passed_time":0.3306204555,"remaining_time":1.685357932},
{"learn":[4.85697213],"iteration":164,"passed_time":0.3317358701,"remaining_time":1.678784555},
{"learn":[4.85382487],"iteration":165,"passed_time":0.3326640571,"remaining_time":1.671336287},
{"learn":[4.84811026],"iteration":166,"passed_time":0.3336756993,"remaining_time":1.66438238},
{"learn":[4.843311226],"iteration":167,"passed_time":0.3347000487,"remaining_time":1.657562146},
{"learn":[4.839933311],"iteration":168,"passed_time":0.3357445696,"remaining_time":1.650909688},
{"learn":[4.837146868],"iteration":169,"passed_time":0.336757163,"remaining_time":1.644167325},
{"learn":[4.830377728],"iteration":170,"passed_time":0.337785953,"remaining_time":1.637570497},
{"learn":[4.824989695],"iteration":171,"passed_time":0.3387708803,"remaining_time":1.630827261},
{"learn":[4.818860885],"iteration":172,"passed_time":0.339740362,"remaining_time":1.624076759},
{"learn":[4.813834544],"iteration":173,"passed_time":0.3407381611,"remaining_time":1.617527133},
{"learn":[4.810205914],"iteration":174,"passed_time":0.3417627856,"remaining_time":1.611167418},
{"learn":[4.80179826],"iteration":175,"passed_time":0.34283265,"remaining_time":1.605080134},
{"learn":[4.797803182],"iteration":176,"passed_time":0.3439597448,"remaining_time":1.599315649},
{"learn":[4.793210255],"iteration":177,"passed_time":0.3450102087,"remaining_time":1.593249391},
{"learn":[4.788923443],"iteration":178,"passed_time":0.3459213833,"remaining_time":1.586600311},
{"learn":[4.783007055],"iteration":179,"passed_time":0.3469275134,"remaining_time":1.580447561},
{"learn":[4.779973139],"iteration":180,"passed_time":0.3478390184,"remaining_time":1.573923514},
{"learn":[4.777132637],"iteration":181,"passed_time":0.3489146304,"remaining_time":1.568198723},
{"learn":[4.772012428],"iteration":182,"passed_time":0.3500018176,"remaining_time":1.562576421},
{"learn":[4.76915089],"iteration":183,"passed_time":0.3509911255,"remaining_time":1.556569339},
{"learn":[4.765335997],"iteration":184,"passed_time":0.3519643321,"remaining_time":1.550545571},
{"learn":[4.760865432],"iteration":185,"passed_time":0.3528058145,"remaining_time":1.54399964},
{"learn":[4.757261871],"iteration":186,"passed_time":0.3537060747,"remaining_time":1.53777026},
{"learn":[4.754462058],"iteration":187,"passed_time":0.3545783779,"remaining_time":1.531476823},
{"learn":[4.751416897],"iteration":188,"passed_time":0.3554296232,"remaining_time":1.525150394},
{"learn":[4.74785502],"iteration":189,"passed_time":0.3563175818,"remaining_time":1.519038112},
{"learn":[4.743962432],"iteration":190,"passed_time":0.3571540977,"remaining_time":1.512762644},
{"learn":[4.741534045],"iteration":191,"passed_time":0.3580112509,"remaining_time":1.506630681},
{"learn":[4.738176786],"iteration":192,"passed_time":0.3589006967,"remaining_time":1.500688405},
{"learn":[4.734623817],"iteration":193,"passed_time":0.3597214117,"remaining_time":1.494512669},
{"learn":[4.730285469],"iteration":194,"passed_time":0.3605520098,"remaining_time":1.488432656},
{"learn":[4.727097576],"iteration":195,"passed_time":0.3614688118,"remaining_time":1.48275982},
{"learn":[4.722578707],"iteration":196,"passed_time":0.3623252139,"remaining_time":1.47688907},
{"learn":[4.719755581],"iteration":197,"passed_time":0.3632056731,"remaining_time":1.471166413},
{"learn":[4.716315725],"iteration":198,"passed_time":0.3640721386,"remaining_time":1.465436096},
{"learn":[4.712630655],"iteration":199,"passed_time":0.364909806,"remaining_time":1.459639224},
{"learn":[4.709380095],"iteration":200,"passed_time":0.3657403039,"remaining_time":1.453863198},
{"learn":[4.706872855],"iteration":201,"passed_time":0.3665786322,"remaining_time":1.448167072},
{"learn":[4.702255036],"iteration":202,"passed_time":0.3674131354,"remaining_time":1.442503788},
{"learn":[4.697322881],"iteration":203,"passed_time":0.3682414104,"remaining_time":1.436863542},
{"learn":[4.694479216],"iteration":204,"passed_time":0.3691763664,"remaining_time":1.431683957},
{"learn":[4.690452281],"iteration":205,"passed_time":0.3700176586,"remaining_time":1.426184568},
{"learn":[4.685485762],"iteration":206,"passed_time":0.3708997046,"remaining_time":1.420886308},
{"learn":[4.683692176],"iteration":207,"passed_time":0.3717348287,"remaining_time":1.415451848},
{"learn":[4.680837926],"iteration":208,"passed_time":0.3725755101,"remaining_time":1.410082433},
{"learn":[4.676032729],"iteration":209,"passed_time":0.3733816057,"remaining_time":1.404626041},
{"learn":[4.67253911],"iteration":210,"passed_time":0.3742665957,"remaining_time":1.399508739},
{"learn":[4.667946458],"iteration":211,"passed_time":0.3750843167,"remaining_time":1.394181328},
{"learn":[4.666512978],"iteration":212,"passed_time":0.3759239167,"remaining_time":1.388977101},
{"learn":[4.66088874],"iteration":213,"passed_time":0.3767285304,"remaining_time":1.383685163},
{"learn":[4.655961219],"iteration":214,"passed_time":0.3777251827,"remaining_time":1.379136132},
{"learn":[4.652698502],"iteration":215,"passed_time":0.378613252,"remaining_time":1.374225877},
{"learn":[4.647224868],"iteration":216,"passed_time":0.379490732,"remaining_time":1.369314485},
{"learn":[4.641907175],"iteration":217,"passed_time":0.3803447009,"remaining_time":1.364355762},
{"learn":[4.636534841],"iteration":218,"passed_time":0.3812281789,"remaining_time":1.359539761},
{"learn":[4.634631581],"iteration":219,"passed_time":0.3820871645,"remaining_time":1.354672674},
{"learn":[4.631808887],"iteration":220,"passed_time":0.3829200055,"remaining_time":1.349749703},
{"learn":[4.627925353],"iteration":221,"passed_time":0.3837757468,"remaining_time":1.344943833},
{"learn":[4.623805793],"iteration":222,"passed_time":0.3846274227,"remaining_time":1.340159226},
{"learn":[4.622086317],"iteration":223,"passed_time":0.3854781073,"remaining_time":1.3354063},
{"learn":[4.615379745],"iteration":224,"passed_time":0.3863763047,"remaining_time":1.330851716},
{"learn":[4.611118123],"iteration":225,"passed_time":0.3872612646,"remaining_time":1.326284154},
{"learn":[4.608591777],"iteration":226,"passed_time":0.3880972298,"remaining_time":1.321582197},
{"learn":[4.605411687],"iteration":227,"passed_time":0.3889252945,"remaining_time":1.316887401},
{"learn":[4.600515603],"iteration":228,"passed_time":0.3897696107,"remaining_time":1.312281091},
{"learn":[4.597878961],"iteration":229,"passed_time":0.3906100417,"remaining_time":1.307694487},
{"learn":[4.590919794],"iteration":230,"passed_time":0.3915415331,"remaining_time":1.303443459},
{"learn":[4.587989694],"iteration":231,"passed_time":0.3923920375,"remaining_time":1.298952952},
{"learn":[4.584376873],"iteration":232,"passed_time":0.3932792104,"remaining_time":1.294614396},
{"learn":[4.582727096],"iteration":233,"passed_time":0.3942169829,"remaining_time":1.290470978},
{"learn":[4.581323198],"iteration":234,"passed_time":0.3951106868,"remaining_time":1.286211385},
{"learn":[4.578021191],"iteration":235,"passed_time":0.3959301902,"remaining_time":1.281740107},
{"learn":[4.575458658],"iteration":236,"passed_time":0.396766656,"remaining_time":1.277354255},
{"learn":[4.569735412],"iteration":237,"passed_time":0.3976081985,"remaining_time":1.273014484},
{"learn":[4.56665856],"iteration":238,"passed_time":0.3984510027,"remaining_time":1.268708004},
{"learn":[4.56494553],"iteration":239,"passed_time":0.3993409993,"remaining_time":1.264579831},
{"learn":[4.56084896],"iteration":240,"passed_time":0.4002458455,"remaining_time":1.260525298},
{"learn":[4.557520861],"iteration":241,"passed_time":0.401133734,"remaining_time":1.256443679},
{"learn":[4.553356258],"iteration":242,"passed_time":0.401944576,"remaining_time":1.252148329},
{"learn":[4.548812976],"iteration":243,"passed_time":0.4028277535,"remaining_time":1.248105663},
{"learn":[4.546306841],"iteration":244,"passed_time":0.4037104805,"remaining_time":1.244087399},
{"learn":[4.543153155],"iteration":245,"passed_time":0.4045845861,"remaining_time":1.240068203},
{"learn":[4.537782226],"iteration":246,"passed_time":0.4055117818,"remaining_time":1.236236323},
{"learn":[4.536035559],"iteration":247,"passed_time":0.4063875596,"remaining_time":1.232271955},
{"learn":[4.53354006],"iteration":248,"passed_time":0.407249429,"remaining_time":1.228290446},
{"learn":[4.532838262],"iteration":249,"passed_time":0.4080561955,"remaining_time":1.224168587},
{"learn":[4.529205715],"iteration":250,"passed_time":0.4089185456,"remaining_time":1.220239006},
{"learn":[4.525668628],"iteration":251,"passed_time":0.4097754584,"remaining_time":1.21631763},
{"learn":[4.524081217],"iteration":252,"passed_time":0.4106668468,"remaining_time":1.212522271},
{"learn":[4.522829458],"iteration":253,"passed_time":0.411500539,"remaining_time":1.208580323},
{"learn":[4.521392185],"iteration":254,"passed_time":0.4123085371,"remaining_time":1.204587687},
{"learn":[4.517579771],"iteration":255,"passed_time":0.4131952494,"remaining_time":1.200848693},
{"learn":[4.513321677],"iteration":256,"passed_time":0.4141403688,"remaining_time":1.197300755},
{"learn":[4.511117293],"iteration":257,"passed_time":0.4149626258,"remaining_time":1.193419645},
{"learn":[4.507171783],"iteration":258,"passed_time":0.4158332268,"remaining_time":1.189700467},
{"learn":[4.506526611],"iteration":259,"passed_time":0.4166399032,"remaining_time":1.185821263},
{"learn":[4.505306728],"iteration":260,"passed_time":0.4174716528,"remaining_time":1.182036595},
{"learn":[4.50222346],"iteration":261,"passed_time":0.4183418732,"remaining_time":1.178382834},
{"learn":[4.497338796],"iteration":262,"passed_time":0.4191675648,"remaining_time":1.174625457},
{"learn":[4.495772509],"iteration":263,"passed_time":0.4201479437,"remaining_time":1.17132154},
{"learn":[4.492187614],"iteration":264,"passed_time":0.4211421351,"remaining_time":1.168073469},
{"learn":[4.486153532],"iteration":265,"passed_time":0.4220857455,"remaining_time":1.164702771},
{"learn":[4.481833017],"iteration":266,"passed_time":0.4229838928,"remaining_time":1.161225444},
{"learn":[4.481177305],"iteration":267,"passed_time":0.4238352183,"remaining_time":1.157639477},
{"learn":[4.478813359],"iteration":268,"passed_time":0.4246649151,"remaining_time":1.154015067},
{"learn":[4.47743371],"iteration":269,"passed_time":0.4255174922,"remaining_time":1.15047322},
{"learn":[4.476001525],"iteration":270,"passed_time":0.4263708504,"remaining_time":1.146953321},
{"learn":[4.471966333],"iteration":271,"passed_time":0.427200397,"remaining_time":1.143389298},
{"learn":[4.469800961],"iteration":272,"passed_time":0.4280631376,"remaining_time":1.139933703},
{"learn":[4.468469562],"iteration":273,"passed_time":0.4289178475,"remaining_time":1.136475756},
{"learn":[4.464103725],"iteration":274,"passed_time":0.4297470036,"remaining_time":1.132969373},
{"learn":[4.461944957],"iteration":275,"passed_time":0.4306062496,"remaining_time":1.129561321},
{"learn":[4.460777825],"iteration":276,"passed_time":0.4314140975,"remaining_time":1.126037518},
{"learn":[4.45633192],"iteration":277,"passed_time":0.4322474993,"remaining_time":1.12259962},
{"learn":[4.452732669],"iteration":278,"passed_time":0.4331308971,"remaining_time":1.119309594},
{"learn":[4.449390035],"iteration":279,"passed_time":0.4339927065,"remaining_time":1.115981245},
{"learn":[4.446032936],"iteration":280,"passed_time":0.4348508709,"remaining_time":1.112661125},
{"learn":[4.439966048],"iteration":281,"passed_time":0.4357574194,"remaining_time":1.109481656},
{"learn":[4.436083776],"iteration":282,"passed_time":0.4366189684,"remaining_time":1.106204241},
{"learn":[4.434526582],"iteration":283,"passed_time":0.4374796061,"remaining_time":1.102941542},
{"learn":[4.432971931],"iteration":284,"passed_time":0.4384494282,"remaining_time":1.099969618},
{"learn":[4.429455808],"iteration":285,"passed_time":0.4393096955,"remaining_time":1.096738191},
{"learn":[4.42436493],"iteration":286,"passed_time":0.440151188,"remaining_time":1.093476645},
{"learn":[4.420668173],"iteration":287,"passed_time":0.4409714724,"remaining_time":1.090179473},
{"learn":[4.418450061],"iteration":288,"passed_time":0.4418328311,"remaining_time":1.087000495},
{"learn":[4.415790801],"iteration":289,"passed_time":0.4427166295,"remaining_time":1.083892438},
{"learn":[4.410545906],"iteration":290,"passed_time":0.443592197,"remaining_time":1.080779614},
{"learn":[4.405680929],"iteration":291,"passed_time":0.4444552479,"remaining_time":1.077651766},
{"learn":[4.402895281],"iteration":292,"passed_time":0.4452967404,"remaining_time":1.074487356},
{"learn":[4.397612952],"iteration":293,"passed_time":0.4461968303,"remaining_time":1.071479463},
{"learn":[4.39383632],"iteration":294,"passed_time":0.4470267475,"remaining_time":1.068318159},
{"learn":[4.391878614],"iteration":295,"passed_time":0.4478288478,"remaining_time":1.065106449},
{"learn":[4.385841633],"iteration":296,"passed_time":0.448724622,"remaining_time":1.062132691},
{"learn":[4.380878882],"iteration":297,"passed_time":0.4496279763,"remaining_time":1.059190736},
{"learn":[4.38044514],"iteration":298,"passed_time":0.4504561011,"remaining_time":1.056086043},
{"learn":[4.376971078],"iteration":299,"passed_time":0.4513132542,"remaining_time":1.05306426},
{"learn":[4.375687999],"iteration":300,"passed_time":0.4522116543,"remaining_time":1.050152646},
{"learn":[4.373134123],"iteration":301,"passed_time":0.4531895919,"remaining_time":1.047438196},
{"learn":[4.369710088],"iteration":302,"passed_time":0.4541054178,"remaining_time":1.044592331},
{"learn":[4.368890473],"iteration":303,"passed_time":0.4549867806,"remaining_time":1.041680261},
{"learn":[4.363232571],"iteration":304,"passed_time":0.4558870131,"remaining_time":1.038824505},
{"learn":[4.359297989],"iteration":305,"passed_time":0.4567882946,"remaining_time":1.03598391},
{"learn":[4.358171343],"iteration":306,"passed_time":0.4576407816,"remaining_time":1.033045803},
{"learn":[4.35451105],"iteration":307,"passed_time":0.4585099707,"remaining_time":1.030158765},
{"learn":[4.352765203],"iteration":308,"passed_time":0.4593300949,"remaining_time":1.027175067},
{"learn":[4.351189376],"iteration":309,"passed_time":0.4602154353,"remaining_time":1.024350485},
{"learn":[4.346813869],"iteration":310,"passed_time":0.461068453,"remaining_time":1.021466766},
{"learn":[4.34390887],"iteration":311,"passed_time":0.461911928,"remaining_time":1.018575021},
{"learn":[4.3400766],"iteration":312,"passed_time":0.462833256,"remaining_time":1.015867242},
{"learn":[4.33910085],"iteration":313,"passed_time":0.4637386778,"remaining_time":1.013136092},
{"learn":[4.335017187],"iteration":314,"passed_time":0.4647373909,"remaining_time":1.010619406},
{"learn":[4.33074149],"iteration":315,"passed_time":0.4656857218,"remaining_time":1.008003271},
{"learn":[4.329616176],"iteration":316,"passed_time":0.4666165552,"remaining_time":1.00535996},
{"learn":[4.326193169],"iteration":317,"passed_time":0.4676667907,"remaining_time":1.002983495},
{"learn":[4.319429595],"iteration":318,"passed_time":0.4688144079,"remaining_time":1.000823234},
{"learn":[4.318293178],"iteration":319,"passed_time":0.4699290114,"remaining_time":0.9985991492},
{"learn":[4.315630221],"iteration":320,"passed_time":0.4709979245,"remaining_time":0.9962853294},
{"learn":[4.309966524],"iteration":321,"passed_time":0.4720421979,"remaining_time":0.9939273608},
{"learn":[4.306823834],"iteration":322,"passed_time":0.4730788083,"remaining_time":0.991561465},
{"learn":[4.301790715],"iteration":323,"passed_time":0.4740375782,"remaining_time":0.9890413668},
{"learn":[4.299768472],"iteration":324,"passed_time":0.4751540942,"remaining_time":0.9868585033},
{"learn":[4.298069468],"iteration":325,"passed_time":0.4762444132,"remaining_time":0.9846280199},
{"learn":[4.296908766],"iteration":326,"passed_time":0.4772946588,"remaining_time":0.9823220347},
{"learn":[4.296268175],"iteration":327,"passed_time":0.4781881929,"remaining_time":0.9797026391},
{"learn":[4.295305871],"iteration":328,"passed_time":0.4791818136,"remaining_time":0.977297863},
{"learn":[4.291820279],"iteration":329,"passed_time":0.4801212956,"remaining_time":0.9747917214},
{"learn":[4.29017626],"iteration":330,"passed_time":0.4810994687,"remaining_time":0.9723732465},
{"learn":[4.28980552],"iteration":331,"passed_time":0.4819389686,"remaining_time":0.9696844307},
{"learn":[4.286363387],"iteration":332,"passed_time":0.4830315329,"remaining_time":0.967513611},
{"learn":[4.282386983],"iteration":333,"passed_time":0.4841356726,"remaining_time":0.9653723292},
{"learn":[4.276488213],"iteration":334,"passed_time":0.4853000166,"remaining_time":0.9633567494},
{"learn":[4.275501997],"iteration":335,"passed_time":0.4865257814,"remaining_time":0.9614676156},
{"learn":[4.271681122],"iteration":336,"passed_time":0.4876942771,"remaining_time":0.9594697498},
{"learn":[4.265928388],"iteration":337,"passed_time":0.4888411933,"remaining_time":0.9574345265},
{"learn":[4.263217708],"iteration":338,"passed_time":0.4898918523,"remaining_time":0.9552168565},
{"learn":[4.260564009],"iteration":339,"passed_time":0.4911522085,"remaining_time":0.9534131105},
{"learn":[4.256949045],"iteration":340,"passed_time":0.4922997202,"remaining_time":0.951394474},
{"learn":[4.255346381],"iteration":341,"passed_time":0.4933641217,"remaining_time":0.9492210294},
{"learn":[4.251392896],"iteration":342,"passed_time":0.4945580009,"remaining_time":0.9473020601},
{"learn":[4.250195534],"iteration":343,"passed_time":0.4956533838,"remaining_time":0.945199476},
{"learn":[4.248132741],"iteration":344,"passed_time":0.4967492678,"remaining_time":0.9431036823},
{"learn":[4.243915606],"iteration":345,"passed_time":0.497823588,"remaining_time":0.9409729092},
{"learn":[4.238677138],"iteration":346,"passed_time":0.4989342463,"remaining_time":0.9389166076},
{"learn":[4.235287453],"iteration":347,"passed_time":0.4999967409,"remaining_time":0.9367755031},
{"learn":[4.233337962],"iteration":348,"passed_time":0.5011005392,"remaining_time":0.9347176247},
{"learn":[4.232741514],"iteration":349,"passed_time":0.5021303616,"remaining_time":0.9325278144},
{"learn":[4.229486506],"iteration":350,"passed_time":0.5034321773,"remaining_time":0.9308475302},
{"learn":[4.225393845],"iteration":351,"passed_time":0.5045086957,"remaining_time":0.9287546444},
{"learn":[4.222272934],"iteration":352,"passed_time":0.505445303,"remaining_time":0.9264110794},
{"learn":[4.219088946],"iteration":353,"passed_time":0.5063443916,"remaining_time":0.924006997},
{"learn":[4.214308299],"iteration":354,"passed_time":0.5071812379,"remaining_time":0.9214983054},
{"learn":[4.211870307],"iteration":355,"passed_time":0.5080454904,"remaining_time":0.9190485838},
{"learn":[4.208440018],"iteration":356,"passed_time":0.5089032644,"remaining_time":0.9165960757},
{"learn":[4.204738859],"iteration":357,"passed_time":0.5098852483,"remaining_time":0.9143752218},
{"learn":[4.202698755],"iteration":358,"passed_time":0.5108059698,"remaining_time":0.9120518848},
{"learn":[4.201104334],"iteration":359,"passed_time":0.5117954278,"remaining_time":0.9098585384},
{"learn":[4.199839686],"iteration":360,"passed_time":0.5127422286,"remaining_time":0.9075963547},
{"learn":[4.19855374],"iteration":361,"passed_time":0.5137090176,"remaining_time":0.9053766664},
{"learn":[4.197466871],"iteration":362,"passed_time":0.5147298262,"remaining_time":0.9032586757},
{"learn":[4.193704216],"iteration":363,"passed_time":0.5157910748,"remaining_time":0.9012173725},
{"learn":[4.192929371],"iteration":364,"passed_time":0.5168527937,"remaining_time":0.8991822575},
{"learn":[4.189541521],"iteration":365,"passed_time":0.5179412526,"remaining_time":0.8971987819},
{"learn":[4.184930112],"iteration":366,"passed_time":0.5189617017,"remaining_time":0.8951028805},
{"learn":[4.184608374],"iteration":367,"passed_time":0.5199452967,"remaining_time":0.8929495313},
{"learn":[4.1836704],"iteration":368,"passed_time":0.5208884936,"remaining_time":0.8907334403},
{"learn":[4.180519324],"iteration":369,"passed_time":0.521889322,"remaining_time":0.888622359},
{"learn":[4.178233947],"iteration":370,"passed_time":0.5228427724,"remaining_time":0.8864369376},
{"learn":[4.175791141],"iteration":371,"passed_time":0.5237891335,"remaining_time":0.8842461716},
{"learn":[4.172792709],"iteration":372,"passed_time":0.524735755,"remaining_time":0.8820625157},
{"learn":[4.167511519],"iteration":373,"passed_time":0.5257250528,"remaining_time":0.8799569066},
{"learn":[4.165146689],"iteration":374,"passed_time":0.5266444683,"remaining_time":0.8777407805},
{"learn":[4.160239089],"iteration":375,"passed_time":0.5275531796,"remaining_time":0.8755137874},
{"learn":[4.159006657],"iteration":376,"passed_time":0.5285152362,"remaining_time":0.873381942},
{"learn":[4.157462744],"iteration":377,"passed_time":0.5294801771,"remaining_time":0.8712610321},
{"learn":[4.154140194],"iteration":378,"passed_time":0.5305670988,"remaining_time":0.8693460906},
{"learn":[4.151280097],"iteration":379,"passed_time":0.5316445732,"remaining_time":0.8674200931},
{"learn":[4.150869963],"iteration":380,"passed_time":0.5327794587,"remaining_time":0.865591824},
{"learn":[4.148746885],"iteration":381,"passed_time":0.5339726909,"remaining_time":0.8638615785},
{"learn":[4.147696672],"iteration":382,"passed_time":0.5349325251,"remaining_time":0.8617581409},
{"learn":[4.144832099],"iteration":383,"passed_time":0.5360264203,"remaining_time":0.8598757158},
{"learn":[4.140145098],"iteration":384,"passed_time":0.5369932193,"remaining_time":0.8577943633},
{"learn":[4.138047241],"iteration":385,"passed_time":0.5379539194,"remaining_time":0.8557090842},
{"learn":[4.137252906],"iteration":386,"passed_time":0.5389214484,"remaining_time":0.8536404338},
{"learn":[4.131978675],"iteration":387,"passed_time":0.5399565368,"remaining_time":0.851684022},
{"learn":[4.129885877],"iteration":388,"passed_time":0.5409298335,"remaining_time":0.8496352912},
{"learn":[4.129400898],"iteration":389,"passed_time":0.5420026318,"remaining_time":0.8477477061},
{"learn":[4.124040192],"iteration":390,"passed_time":0.5430263051,"remaining_time":0.8457877744},
{"learn":[4.121562658],"iteration":391,"passed_time":0.5441236457,"remaining_time":0.8439468791},
{"learn":[4.120224742],"iteration":392,"passed_time":0.5451098295,"remaining_time":0.8419380827},
{"learn":[4.117524705],"iteration":393,"passed_time":0.5460424772,"remaining_time":0.839852135},
{"learn":[4.115245504],"iteration":394,"passed_time":0.5470442315,"remaining_time":0.8378778736},
{"learn":[4.113466796],"iteration":395,"passed_time":0.5479812546,"remaining_time":0.8358097923},
{"learn":[4.110265013],"iteration":396,"passed_time":0.5489443988,"remaining_time":0.8337870843},
{"learn":[4.107099844],"iteration":397,"passed_time":0.5499580188,"remaining_time":0.8318460485},
{"learn":[4.104680732],"iteration":398,"passed_time":0.5509596029,"remaining_time":0.8298915322},
{"learn":[4.102349357],"iteration":399,"passed_time":0.5519627991,"remaining_time":0.8279441987},
{"learn":[4.097409957],"iteration":400,"passed_time":0.5529823369,"remaining_time":0.8260259846},
{"learn":[4.094142546],"iteration":401,"passed_time":0.5539824491,"remaining_time":0.8240833447},
{"learn":[4.094002912],"iteration":402,"passed_time":0.5549978314,"remaining_time":0.8221680034},
{"learn":[4.090716238],"iteration":403,"passed_time":0.5560537173,"remaining_time":0.8203168701},
{"learn":[4.087957488],"iteration":404,"passed_time":0.5571385715,"remaining_time":0.8185122223},
{"learn":[4.082747858],"iteration":405,"passed_time":0.5580846822,"remaining_time":0.8165081312},
{"learn":[4.077908438],"iteration":406,"passed_time":0.5591928272,"remaining_time":0.8147453232},
{"learn":[4.075335484],"iteration":407,"passed_time":0.5603580367,"remaining_time":0.8130685238},
{"learn":[4.070498954],"iteration":408,"passed_time":0.5613932509,"remaining_time":0.8112063846},
{"learn":[4.069248402],"iteration":409,"passed_time":0.5624234171,"remaining_time":0.8093410148},
{"learn":[4.06631603],"iteration":410,"passed_time":0.563538382,"remaining_time":0.8076012336},
{"learn":[4.065051681],"iteration":411,"passed_time":0.5646397881,"remaining_time":0.8058451345},
{"learn":[4.061941405],"iteration":412,"passed_time":0.5656104413,"remaining_time":0.8039063657},
{"learn":[4.060542483],"iteration":413,"passed_time":0.5667046969,"remaining_time":0.802147228},
{"learn":[4.058642899],"iteration":414,"passed_time":0.5677293725,"remaining_time":0.8002932119},
{"learn":[4.058026321],"iteration":415,"passed_time":0.568718535,"remaining_time":0.7983933279},
{"learn":[4.055761676],"iteration":416,"passed_time":0.5696659975,"remaining_time":0.7964395121},
{"learn":[4.052577138],"iteration":417,"passed_time":0.570646499,"remaining_time":0.7945365129},
{"learn":[4.051912877],"iteration":418,"passed_time":0.57165332,"remaining_time":0.7926744127},
{"learn":[4.049018496],"iteration":419,"passed_time":0.5727710824,"remaining_time":0.79096959},
{"learn":[4.047695104],"iteration":420,"passed_time":0.573789433,"remaining_time":0.7891308354},
{"learn":[4.044867447],"iteration":421,"passed_time":0.5748807414,"remaining_time":0.787395897},
{"learn":[4.042097059],"iteration":422,"passed_time":0.5759107583,"remaining_time":0.7855803961},
{"learn":[4.039943404],"iteration":423,"passed_time":0.5769987166,"remaining_time":0.7838473131},
{"learn":[4.037506406],"iteration":424,"passed_time":0.5780205074,"remaining_time":0.7820277453},
{"learn":[4.03287622],"iteration":425,"passed_time":0.5791001046,"remaining_time":0.7802898123},
{"learn":[4.027096138],"iteration":426,"passed_time":0.5803073106,"remaining_time":0.7787262036},
{"learn":[4.024901471],"iteration":427,"passed_time":0.5813707164,"remaining_time":0.7769720789},
{"learn":[4.021934734],"iteration":428,"passed_time":0.5824996235,"remaining_time":0.7753083568},
{"learn":[4.017197009],"iteration":429,"passed_time":0.5834860476,"remaining_time":0.7734582491},
{"learn":[4.014523633],"iteration":430,"passed_time":0.584479295,"remaining_time":0.7716211574},
{"learn":[4.012499807],"iteration":431,"passed_time":0.5854952481,"remaining_time":0.7698178261},
{"learn":[4.011397549],"iteration":432,"passed_time":0.586526335,"remaining_time":0.768037949},
{"learn":[4.008621049],"iteration":433,"passed_time":0.5874801359,"remaining_time":0.7661607302},
{"learn":[4.007354109],"iteration":434,"passed_time":0.5884236704,"remaining_time":0.7642744224},
{"learn":[4.004795142],"iteration":435,"passed_time":0.5894405299,"remaining_time":0.762487291},
{"learn":[4.000788482],"iteration":436,"passed_time":0.5904368518,"remaining_time":0.7606772256},
{"learn":[3.999981616],"iteration":437,"passed_time":0.5913361636,"remaining_time":0.7587464016},
{"learn":[3.997814776],"iteration":438,"passed_time":0.5922655694,"remaining_time":0.7568587344},
{"learn":[3.994587527],"iteration":439,"passed_time":0.593333381,"remaining_time":0.7551515758},
{"learn":[3.992927465],"iteration":440,"passed_time":0.594479171,"remaining_time":0.7535461601},
{"learn":[3.990359818],"iteration":441,"passed_time":0.5954494113,"remaining_time":0.7517212025},
{"learn":[3.989100503],"iteration":442,"passed_time":0.5964863693,"remaining_time":0.7499839903},
{"learn":[3.98685997],"iteration":443,"passed_time":0.597408278,"remaining_time":0.7481058617},
{"learn":[3.983067345],"iteration":444,"passed_time":0.5983671685,"remaining_time":0.746278154},
{"learn":[3.982112551],"iteration":445,"passed_time":0.5993269846,"remaining_time":0.744455492},
{"learn":[3.981200263],"iteration":446,"passed_time":0.6004315548,"remaining_time":0.7428157714},
{"learn":[3.97674387],"iteration":447,"passed_time":0.601396891,"remaining_time":0.7410068835},
{"learn":[3.975551867],"iteration":448,"passed_time":0.6022627957,"remaining_time":0.7390797337},
{"learn":[3.971588145],"iteration":449,"passed_time":0.6031216211,"remaining_time":0.737148648},
{"learn":[3.967494455],"iteration":450,"passed_time":0.6039780132,"remaining_time":0.7352193553},
{"learn":[3.962930511],"iteration":451,"passed_time":0.6048380402,"remaining_time":0.7332992168},
{"learn":[3.962054313],"iteration":452,"passed_time":0.6056683178,"remaining_time":0.7313478363},
{"learn":[3.959643845],"iteration":453,"passed_time":0.6065110719,"remaining_time":0.7294163993},
{"learn":[3.958470184],"iteration":454,"passed_time":0.607445297,"remaining_time":0.7275993118},
{"learn":[3.955637175],"iteration":455,"passed_time":0.6083236481,"remaining_time":0.7257194399},
{"learn":[3.952260431],"iteration":456,"passed_time":0.6092106007,"remaining_time":0.7238541711},
{"learn":[3.950460588],"iteration":457,"passed_time":0.6100938884,"remaining_time":0.7219888374},
{"learn":[3.946229064],"iteration":458,"passed_time":0.6109333281,"remaining_time":0.7200761014},
{"learn":[3.945085454],"iteration":459,"passed_time":0.6117641265,"remaining_time":0.7181578876},
{"learn":[3.94086169],"iteration":460,"passed_time":0.6126561157,"remaining_time":0.7163159357},
{"learn":[3.936695153],"iteration":461,"passed_time":0.6137563101,"remaining_time":0.7147205516},
{"learn":[3.935389],"iteration":462,"passed_time":0.6148816078,"remaining_time":0.713156422},
{"learn":[3.932973377],"iteration":463,"passed_time":0.6160659535,"remaining_time":0.7116623945},
{"learn":[3.930107444],"iteration":464,"passed_time":0.6169776588,"remaining_time":0.709856016},
{"learn":[3.928999984],"iteration":465,"passed_time":0.6178672248,"remaining_time":0.7080281073},
{"learn":[3.925993012],"iteration":466,"passed_time":0.6187699281,"remaining_time":0.7062192113},
{"learn":[3.923140165],"iteration":467,"passed_time":0.6196908956,"remaining_time":0.7044349498},
{"learn":[3.922955382],"iteration":468,"passed_time":0.6204966509,"remaining_time":0.7025239267},
{"learn":[3.919414601],"iteration":469,"passed_time":0.6214174882,"remaining_time":0.7007473803},
{"learn":[3.919103142],"iteration":470,"passed_time":0.6224463074,"remaining_time":0.6990957465},
{"learn":[3.915301534],"iteration":471,"passed_time":0.6233801528,"remaining_time":0.69734051},
{"learn":[3.914394619],"iteration":472,"passed_time":0.6242653331,"remaining_time":0.6955345254},
{"learn":[3.912369708],"iteration":473,"passed_time":0.6251335399,"remaining_time":0.6937135907},
{"learn":[3.910122005],"iteration":474,"passed_time":0.6259916843,"remaining_time":0.6918855458},
{"learn":[3.907471795],"iteration":475,"passed_time":0.626860533,"remaining_time":0.6900733598},
{"learn":[3.90717309],"iteration":476,"passed_time":0.6278110705,"remaining_time":0.6883546958},
{"learn":[3.906221052],"iteration":477,"passed_time":0.6286738912,"remaining_time":0.6865434544},
{"learn":[3.904691253],"iteration":478,"passed_time":0.6295427798,"remaining_time":0.6847427731},
{"learn":[3.904102999],"iteration":479,"passed_time":0.6303494162,"remaining_time":0.6828785342},
{"learn":[3.903498126],"iteration":480,"passed_time":0.6311957041,"remaining_time":0.6810614769},
{"learn":[3.901543043],"iteration":481,"passed_time":0.6321233514,"remaining_time":0.6793358838},
{"learn":[3.90143027],"iteration":482,"passed_time":0.6329429949,"remaining_time":0.6774979884},
{"learn":[3.896396908],"iteration":483,"passed_time":0.6338025613,"remaining_time":0.6757068628},
{"learn":[3.894952721],"iteration":484,"passed_time":0.6346660929,"remaining_time":0.6739237893},
{"learn":[3.894284896],"iteration":485,"passed_time":0.6355052622,"remaining_time":0.6721187341},
{"learn":[3.892193237],"iteration":486,"passed_time":0.6363194486,"remaining_time":0.6702913288},
{"learn":[3.890283233],"iteration":487,"passed_time":0.6372357046,"remaining_time":0.6685751655},
{"learn":[3.888578251],"iteration":488,"passed_time":0.6381071968,"remaining_time":0.666815496},
{"learn":[3.888435772],"iteration":489,"passed_time":0.6389372541,"remaining_time":0.6650163257},
{"learn":[3.883806763],"iteration":490,"passed_time":0.6397598816,"remaining_time":0.6632134007},
{"learn":[3.879897079],"iteration":491,"passed_time":0.6406983175,"remaining_time":0.6615340351},
{"learn":[3.878409869],"iteration":492,"passed_time":0.6420108879,"remaining_time":0.6602424344},
{"learn":[3.877130419],"iteration":493,"passed_time":0.6433609374,"remaining_time":0.6589891384},
{"learn":[3.87602796],"iteration":494,"passed_time":0.644609447,"remaining_time":0.6576318601},
{"learn":[3.871001871],"iteration":495,"passed_time":0.6459456435,"remaining_time":0.6563641216},
{"learn":[3.869874388],"iteration":496,"passed_time":0.6472295217,"remaining_time":0.6550431578},
{"learn":[3.867898328],"iteration":497,"passed_time":0.6483738693,"remaining_time":0.6535816915},
{"learn":[3.865656851],"iteration":498,"passed_time":0.6495703263,"remaining_time":0.6521738145},
{"learn":[3.861654889],"iteration":499,"passed_time":0.6507723453,"remaining_time":0.6507723453},
{"learn":[3.861083447],"iteration":500,"passed_time":0.6518804154,"remaining_time":0.6492780984},
{"learn":[3.860391836],"iteration":501,"passed_time":0.6529020908,"remaining_time":0.6476996838},
{"learn":[3.855654269],"iteration":502,"passed_time":0.6539386312,"remaining_time":0.6461381703},
{"learn":[3.853001042],"iteration":503,"passed_time":0.6553867856,"remaining_time":0.6449838208},
{"learn":[3.85028481],"iteration":504,"passed_time":0.6566284671,"remaining_time":0.6436259232},
{"learn":[3.847024814],"iteration":505,"passed_time":0.6576999036,"remaining_time":0.6421022774},
{"learn":[3.846166686],"iteration":506,"passed_time":0.6587457562,"remaining_time":0.6405555381},
{"learn":[3.84587999],"iteration":507,"passed_time":0.6598499259,"remaining_time":0.6390672511},
{"learn":[3.844496782],"iteration":508,"passed_time":0.6609711729,"remaining_time":0.6375969468},
{"learn":[3.838927045],"iteration":509,"passed_time":0.6621030293,"remaining_time":0.6361382046},
{"learn":[3.835715514],"iteration":510,"passed_time":0.6631547797,"remaining_time":0.6346040847},
{"learn":[3.834893176],"iteration":511,"passed_time":0.6642489214,"remaining_time":0.6331122532},
{"learn":[3.833035171],"iteration":512,"passed_time":0.6654378431,"remaining_time":0.6317119485},
{"learn":[3.830328606],"iteration":513,"passed_time":0.6665952279,"remaining_time":0.6302826474},
{"learn":[3.828946077],"iteration":514,"passed_time":0.6676959631,"remaining_time":0.6288010526},
{"learn":[3.827371859],"iteration":515,"passed_time":0.6688781665,"remaining_time":0.6273973499},
{"learn":[3.82668503],"iteration":516,"passed_time":0.669999538,"remaining_time":0.6259376728},
{"learn":[3.823775345],"iteration":517,"passed_time":0.6710772837,"remaining_time":0.624438708},
{"learn":[3.820231527],"iteration":518,"passed_time":0.672215909,"remaining_time":0.6229977885},
{"learn":[3.81679406],"iteration":519,"passed_time":0.6732859135,"remaining_time":0.6214946894},
{"learn":[3.815539988],"iteration":520,"passed_time":0.6742914576,"remaining_time":0.6199339888},
{"learn":[3.812965355],"iteration":521,"passed_time":0.6754401814,"remaining_time":0.6185065263},
{"learn":[3.811620869],"iteration":522,"passed_time":0.6764929933,"remaining_time":0.6169926535},
{"learn":[3.809261414],"iteration":523,"passed_time":0.6775798501,"remaining_time":0.6155114669},
{"learn":[3.805573184],"iteration":524,"passed_time":0.6786488223,"remaining_time":0.6140156011},
{"learn":[3.801676956],"iteration":525,"passed_time":0.6796795259,"remaining_time":0.6124868731},
{"learn":[3.800073933],"iteration":526,"passed_time":0.6808832801,"remaining_time":0.6111153538},
{"learn":[3.798521337],"iteration":527,"passed_time":0.6819779873,"remaining_time":0.6096469886},
{"learn":[3.797510041],"iteration":528,"passed_time":0.6830434859,"remaining_time":0.60815403},
{"learn":[3.79359831],"iteration":529,"passed_time":0.6841421507,"remaining_time":0.6066920959},
{"learn":[3.79186749],"iteration":530,"passed_time":0.6854450007,"remaining_time":0.6054118744},
{"learn":[3.790309433],"iteration":531,"passed_time":0.6865406091,"remaining_time":0.6039492576},
{"learn":[3.789221221],"iteration":532,"passed_time":0.6876537607,"remaining_time":0.6025033888},
{"learn":[3.786225035],"iteration":533,"passed_time":0.6888978825,"remaining_time":0.6011730585},
{"learn":[3.783130901],"iteration":534,"passed_time":0.6899499033,"remaining_time":0.5996760842},
{"learn":[3.781451005],"iteration":535,"passed_time":0.6910660188,"remaining_time":0.5982362551},
{"learn":[3.777819185],"iteration":536,"passed_time":0.6921462621,"remaining_time":0.5967667027},
{"learn":[3.774165057],"iteration":537,"passed_time":0.6931723987,"remaining_time":0.5952521342},
{"learn":[3.773695334],"iteration":538,"passed_time":0.6942100304,"remaining_time":0.5937492097},
{"learn":[3.771901202],"iteration":539,"passed_time":0.6952867486,"remaining_time":0.5922813044},
{"learn":[3.766578364],"iteration":540,"passed_time":0.6964107746,"remaining_time":0.5908549825},
{"learn":[3.763224447],"iteration":541,"passed_time":0.697587423,"remaining_time":0.589474243},
{"learn":[3.760276632],"iteration":542,"passed_time":0.6986859352,"remaining_time":0.5880284943},
{"learn":[3.75903192],"iteration":543,"passed_time":0.6996668992,"remaining_time":0.586485489},
{"learn":[3.756824663],"iteration":544,"passed_time":0.7007337696,"remaining_time":0.5850162663},
{"learn":[3.75256937],"iteration":545,"passed_time":0.7018032663,"remaining_time":0.5835507013},
{"learn":[3.750445479],"iteration":546,"passed_time":0.7028444899,"remaining_time":0.5820631699},
{"learn":[3.746364752],"iteration":547,"passed_time":0.7042081827,"remaining_time":0.5808432456},
{"learn":[3.746239085],"iteration":548,"passed_time":0.7053109754,"remaining_time":0.5794084698},
{"learn":[3.745077952],"iteration":549,"passed_time":0.7065490374,"remaining_time":0.578085576},
{"learn":[3.742924096],"iteration":550,"passed_time":0.7077054909,"remaining_time":0.576696489},
{"learn":[3.742381459],"iteration":551,"passed_time":0.7089861893,"remaining_time":0.5754090811},
{"learn":[3.738702769],"iteration":552,"passed_time":0.7101830916,"remaining_time":0.5740539637},
{"learn":[3.737207651],"iteration":553,"passed_time":0.7113608233,"remaining_time":0.5726839841},
{"learn":[3.735409665],"iteration":554,"passed_time":0.7124665551,"remaining_time":0.5712569676},
{"learn":[3.735291685],"iteration":555,"passed_time":0.7138313145,"remaining_time":0.5700379562},
{"learn":[3.732892173],"iteration":556,"passed_time":0.7150775268,"remaining_time":0.5687241371},
{"learn":[3.731932914],"iteration":557,"passed_time":0.7161562629,"remaining_time":0.5672779},
{"learn":[3.730508294],"iteration":558,"passed_time":0.717256012,"remaining_time":0.5658495551},
{"learn":[3.728833527],"iteration":559,"passed_time":0.7183237783,"remaining_time":0.5643972544},
{"learn":[3.727616993],"iteration":560,"passed_time":0.7193260662,"remaining_time":0.5628950857},
{"learn":[3.724432189],"iteration":561,"passed_time":0.720495527,"remaining_time":0.5615249837},
{"learn":[3.7223799],"iteration":562,"passed_time":0.7215434876,"remaining_time":0.5600612861},
{"learn":[3.718897257],"iteration":563,"passed_time":0.7226574193,"remaining_time":0.5586500617},
{"learn":[3.717312451],"iteration":564,"passed_time":0.7238485239,"remaining_time":0.557299306},
{"learn":[3.714944981],"iteration":565,"passed_time":0.7250168594,"remaining_time":0.5559316555},
{"learn":[3.711094942],"iteration":566,"passed_time":0.7263842071,"remaining_time":0.5547166872},
{"learn":[3.707060117],"iteration":567,"passed_time":0.7274936037,"remaining_time":0.5533049944},
{"learn":[3.704665542],"iteration":568,"passed_time":0.728599766,"remaining_time":0.5518919142},
{"learn":[3.703733257],"iteration":569,"passed_time":0.7297210431,"remaining_time":0.5504913132},
{"learn":[3.702291144],"iteration":570,"passed_time":0.7308925171,"remaining_time":0.5491294042},
{"learn":[3.701766767],"iteration":571,"passed_time":0.7319928808,"remaining_time":0.5477149528},
{"learn":[3.697750439],"iteration":572,"passed_time":0.7331494207,"remaining_time":0.5463434601},
{"learn":[3.692629485],"iteration":573,"passed_time":0.7341907263,"remaining_time":0.5448871941},
{"learn":[3.689357347],"iteration":574,"passed_time":0.7352394437,"remaining_time":0.5434378497},
{"learn":[3.684463861],"iteration":575,"passed_time":0.7363869798,"remaining_time":0.5420626379},
{"learn":[3.683919587],"iteration":576,"passed_time":0.7376903128,"remaining_time":0.5408024303},
{"learn":[3.682300133],"iteration":577,"passed_time":0.7388789031,"remaining_time":0.5394582995},
{"learn":[3.681306681],"iteration":578,"passed_time":0.740012743,"remaining_time":0.5380748961},
{"learn":[3.679162701],"iteration":579,"passed_time":0.7411280274,"remaining_time":0.5366789164},
{"learn":[3.675552311],"iteration":580,"passed_time":0.7422017021,"remaining_time":0.5352538953},
{"learn":[3.672593509],"iteration":581,"passed_time":0.7434079444,"remaining_time":0.5339252934},
{"learn":[3.672360726],"iteration":582,"passed_time":0.7445060732,"remaining_time":0.5325197814},
{"learn":[3.671363322],"iteration":583,"passed_time":0.7455874628,"remaining_time":0.5311033982},
{"learn":[3.671030128],"iteration":584,"passed_time":0.7466622937,"remaining_time":0.5296835075},
{"learn":[3.670411898],"iteration":585,"passed_time":0.7477770403,"remaining_time":0.5282929943},
{"learn":[3.668474223],"iteration":586,"passed_time":0.7490108485,"remaining_time":0.5269871899},
{"learn":[3.66790084],"iteration":587,"passed_time":0.7500564909,"remaining_time":0.5255497861},
{"learn":[3.665196104],"iteration":588,"passed_time":0.7511075103,"remaining_time":0.5241174648},
{"learn":[3.663589048],"iteration":589,"passed_time":0.7522295885,"remaining_time":0.5227358157},
{"learn":[3.663406551],"iteration":590,"passed_time":0.7532232564,"remaining_time":0.5212661791},
{"learn":[3.660671568],"iteration":591,"passed_time":0.7542768049,"remaining_time":0.5198394196},
{"learn":[3.659131381],"iteration":592,"passed_time":0.7553580042,"remaining_time":0.5184328967},
{"learn":[3.657688389],"iteration":593,"passed_time":0.7564244684,"remaining_time":0.5170173976},
{"learn":[3.654170562],"iteration":594,"passed_time":0.7578683129,"remaining_time":0.515859944},
{"learn":[3.653305374],"iteration":595,"passed_time":0.7592208762,"remaining_time":0.5146396543},
{"learn":[3.649501814],"iteration":596,"passed_time":0.7603107046,"remaining_time":0.5132415644},
{"learn":[3.647508458],"iteration":597,"passed_time":0.7614131491,"remaining_time":0.5118529865},
{"learn":[3.646543564],"iteration":598,"passed_time":0.7625018484,"remaining_time":0.5104561623},
{"learn":[3.644468032],"iteration":599,"passed_time":0.763591559,"remaining_time":0.5090610393},
{"learn":[3.64304542],"iteration":600,"passed_time":0.7646410416,"remaining_time":0.5076402257},
{"learn":[3.641037981],"iteration":601,"passed_time":0.7657486607,"remaining_time":0.5062590813},
{"learn":[3.6378612],"iteration":602,"passed_time":0.7668877094,"remaining_time":0.5048995367},
{"learn":[3.635905084],"iteration":603,"passed_time":0.7679812121,"remaining_time":0.5035108609},
{"learn":[3.632534881],"iteration":604,"passed_time":0.7690893099,"remaining_time":0.5021326899},
{"learn":[3.628286239],"iteration":605,"passed_time":0.7701915642,"remaining_time":0.500751611},
{"learn":[3.626565647],"iteration":606,"passed_time":0.7713191348,"remaining_time":0.4993878418},
{"learn":[3.625665776],"iteration":607,"passed_time":0.7723855346,"remaining_time":0.4979854105},
{"learn":[3.624725183],"iteration":608,"passed_time":0.7736244553,"remaining_time":0.4966948474},
{"learn":[3.621352513],"iteration":609,"passed_time":0.7747279542,"remaining_time":0.4953178723},
{"learn":[3.619760503],"iteration":610,"passed_time":0.7758877746,"remaining_time":0.4939776503},
{"learn":[3.616950899],"iteration":611,"passed_time":0.7772372939,"remaining_time":0.4927582844},
{"learn":[3.615418939],"iteration":612,"passed_time":0.7783085901,"remaining_time":0.4913628457},
{"learn":[3.613093988],"iteration":613,"passed_time":0.7794277187,"remaining_time":0.4899985332},
{"learn":[3.610326343],"iteration":614,"passed_time":0.7806204064,"remaining_time":0.4886810674},
{"learn":[3.607465558],"iteration":615,"passed_time":0.7817305139,"remaining_time":0.4873125282},
{"learn":[3.606769094],"iteration":616,"passed_time":0.7828126145,"remaining_time":0.4859274414},
{"learn":[3.604027941],"iteration":617,"passed_time":0.7838297882,"remaining_time":0.4845032024},
{"learn":[3.602820816],"iteration":618,"passed_time":0.7849274651,"remaining_time":0.4831298291},
{"learn":[3.601146138],"iteration":619,"passed_time":0.7860585356,"remaining_time":0.4817778121},
{"learn":[3.597667423],"iteration":620,"passed_time":0.7871860562,"remaining_time":0.4804243402},
{"learn":[3.595829397],"iteration":621,"passed_time":0.7882650326,"remaining_time":0.4790420937},
{"learn":[3.592185058],"iteration":622,"passed_time":0.7894339379,"remaining_time":0.4777152401},
{"learn":[3.590534912],"iteration":623,"passed_time":0.7910130554,"remaining_time":0.4766360719},
{"learn":[3.589902756],"iteration":624,"passed_time":0.79274869,"remaining_time":0.475649214},
{"learn":[3.589499112],"iteration":625,"passed_time":0.7942379387,"remaining_time":0.4745127621},
{"learn":[3.587309074],"iteration":626,"passed_time":0.7956891472,"remaining_time":0.4733525549},
{"learn":[3.586874947],"iteration":627,"passed_time":0.7966869664,"remaining_time":0.4719228527},
{"learn":[3.585191471],"iteration":628,"passed_time":0.7977565904,"remaining_time":0.4705368761},
{"learn":[3.58432202],"iteration":629,"passed_time":0.7988430167,"remaining_time":0.4691617717},
{"learn":[3.581363489],"iteration":630,"passed_time":0.7999920557,"remaining_time":0.4678241974},
{"learn":[3.580064873],"iteration":631,"passed_time":0.8010567432,"remaining_time":0.4664381036},
{"learn":[3.576418581],"iteration":632,"passed_time":0.8022028684,"remaining_time":0.4651002412},
{"learn":[3.57502894],"iteration":633,"passed_time":0.8033340738,"remaining_time":0.4637543707},
{"learn":[3.57413332],"iteration":634,"passed_time":0.8044193738,"remaining_time":0.4623827897},
{"learn":[3.57362783],"iteration":635,"passed_time":0.8054952562,"remaining_time":0.4610067189},
{"learn":[3.570496761],"iteration":636,"passed_time":0.806630742,"remaining_time":0.4596655563},
{"learn":[3.567887781],"iteration":637,"passed_time":0.8078350093,"remaining_time":0.4583640648},
{"learn":[3.564851294],"iteration":638,"passed_time":0.808993025,"remaining_time":0.4570367481},
{"learn":[3.562438159],"iteration":639,"passed_time":0.810070004,"remaining_time":0.4556643772},
{"learn":[3.559878916],"iteration":640,"passed_time":0.8111252438,"remaining_time":0.4542807527},
{"learn":[3.558326786],"iteration":641,"passed_time":0.8121768139,"remaining_time":0.452896105},
{"learn":[3.555300451],"iteration":642,"passed_time":0.8136997473,"remaining_time":0.4517741987},
{"learn":[3.553092599],"iteration":643,"passed_time":0.8152213889,"remaining_time":0.450650333},
{"learn":[3.551548414],"iteration":644,"passed_time":0.8163057724,"remaining_time":0.4492845724},
{"learn":[3.549806993],"iteration":645,"passed_time":0.8174639936,"remaining_time":0.4479601451},
{"learn":[3.547823236],"iteration":646,"passed_time":0.8187925151,"remaining_time":0.4467291466},
{"learn":[3.547156856],"iteration":647,"passed_time":0.8199281464,"remaining_time":0.4453930672},
{"learn":[3.546045916],"iteration":648,"passed_time":0.8212026661,"remaining_time":0.4441327208},
{"learn":[3.543717543],"iteration":649,"passed_time":0.822432532,"remaining_time":0.4428482865},
{"learn":[3.541158953],"iteration":650,"passed_time":0.8234946361,"remaining_time":0.4414740829},
{"learn":[3.5404206],"iteration":651,"passed_time":0.8246606728,"remaining_time":0.44015631},
{"learn":[3.538056818],"iteration":652,"passed_time":0.8260290466,"remaining_time":0.4389465225},
{"learn":[3.537478573],"iteration":653,"passed_time":0.8271790612,"remaining_time":0.4376207266},
{"learn":[3.535843963],"iteration":654,"passed_time":0.8281722342,"remaining_time":0.4362128562},
{"learn":[3.534160754],"iteration":655,"passed_time":0.829324353,"remaining_time":0.4348895997},
{"learn":[3.532391006],"iteration":656,"passed_time":0.830415721,"remaining_time":0.4335351481},
{"learn":[3.529663242],"iteration":657,"passed_time":0.8315246771,"remaining_time":0.4321906376},
{"learn":[3.528629754],"iteration":658,"passed_time":0.8327153201,"remaining_time":0.430889111},
{"learn":[3.527763114],"iteration":659,"passed_time":0.833995153,"remaining_time":0.4296338667},
{"learn":[3.523440863],"iteration":660,"passed_time":0.8351598828,"remaining_time":0.4283195163},
{"learn":[3.521692212],"iteration":661,"passed_time":0.8364257963,"remaining_time":0.4270572797},
{"learn":[3.520837289],"iteration":662,"passed_time":0.8375646519,"remaining_time":0.425730449},
{"learn":[3.519526807],"iteration":663,"passed_time":0.8386319076,"remaining_time":0.4243679532},
{"learn":[3.516818187],"iteration":664,"passed_time":0.8396987022,"remaining_time":0.4230061131},
{"learn":[3.516361442],"iteration":665,"passed_time":0.8408091912,"remaining_time":0.4216670719},
{"learn":[3.513353734],"iteration":666,"passed_time":0.8419405568,"remaining_time":0.4203391386},
{"learn":[3.511117041],"iteration":667,"passed_time":0.8430360742,"remaining_time":0.418993977},
{"learn":[3.508754766],"iteration":668,"passed_time":0.8440511861,"remaining_time":0.4176097797},
{"learn":[3.506685955],"iteration":669,"passed_time":0.8450785643,"remaining_time":0.4162327257},
{"learn":[3.505660936],"iteration":670,"passed_time":0.8461739977,"remaining_time":0.4148900823},
{"learn":[3.502095034],"iteration":671,"passed_time":0.8473070256,"remaining_time":0.4135665244},
{"learn":[3.501287934],"iteration":672,"passed_time":0.8483976121,"remaining_time":0.4122229111},
{"learn":[3.498826628],"iteration":673,"passed_time":0.8494511492,"remaining_time":0.4108621285},
{"learn":[3.498281286],"iteration":674,"passed_time":0.8506846208,"remaining_time":0.4095888915},
{"learn":[3.495255765],"iteration":675,"passed_time":0.8518032496,"remaining_time":0.4082607291},
{"learn":[3.493058093],"iteration":676,"passed_time":0.8529116897,"remaining_time":0.4069283246},
{"learn":[3.491431469],"iteration":677,"passed_time":0.8539166025,"remaining_time":0.405547413},
{"learn":[3.490549652],"iteration":678,"passed_time":0.8550644056,"remaining_time":0.4042351608},
{"learn":[3.48969794],"iteration":679,"passed_time":0.8561720852,"remaining_time":0.4029045107},
{"learn":[3.486339277],"iteration":680,"passed_time":0.8572704372,"remaining_time":0.4015701461},
{"learn":[3.484431149],"iteration":681,"passed_time":0.8583778512,"remaining_time":0.400240699},
{"learn":[3.483321687],"iteration":682,"passed_time":0.859448787,"remaining_time":0.3988949714},
{"learn":[3.479437754],"iteration":683,"passed_time":0.8605164985,"remaining_time":0.3975485578},
{"learn":[3.478066521],"iteration":684,"passed_time":0.8616157708,"remaining_time":0.3962174712},
{"learn":[3.47681303],"iteration":685,"passed_time":0.8628003568,"remaining_time":0.3949261109},
{"learn":[3.475643368],"iteration":686,"passed_time":0.8639177197,"remaining_time":0.3936044342},
{"learn":[3.473614464],"iteration":687,"passed_time":0.8653051038,"remaining_time":0.3924058029},
{"learn":[3.471384971],"iteration":688,"passed_time":0.8666761463,"remaining_time":0.3911992475},
{"learn":[3.469300251],"iteration":689,"passed_time":0.8679138974,"remaining_time":0.3899323307},
{"learn":[3.466505663],"iteration":690,"passed_time":0.8691110953,"remaining_time":0.3886473639},
{"learn":[3.464930936],"iteration":691,"passed_time":0.870397546,"remaining_time":0.387402376},
{"learn":[3.463795069],"iteration":692,"passed_time":0.8716030044,"remaining_time":0.3861213887},
{"learn":[3.459557938],"iteration":693,"passed_time":0.8728139853,"remaining_time":0.384843054},
{"learn":[3.457454321],"iteration":694,"passed_time":0.8739094836,"remaining_time":0.3835142338},
{"learn":[3.456694091],"iteration":695,"passed_time":0.874993551,"remaining_time":0.3821810912},
{"learn":[3.455192002],"iteration":696,"passed_time":0.8760448017,"remaining_time":0.3808343973},
{"learn":[3.453549034],"iteration":697,"passed_time":0.877141812,"remaining_time":0.3795083484},
{"learn":[3.452805985],"iteration":698,"passed_time":0.8782770527,"remaining_time":0.3781994176},
{"learn":[3.450055568],"iteration":699,"passed_time":0.8794206245,"remaining_time":0.3768945534},
{"learn":[3.448016553],"iteration":700,"passed_time":0.8805259758,"remaining_time":0.375573847},
{"learn":[3.445943413],"iteration":701,"passed_time":0.8815006233,"remaining_time":0.3741982703},
{"learn":[3.445144424],"iteration":702,"passed_time":0.8825684159,"remaining_time":0.3728631857},
{"learn":[3.443042949],"iteration":703,"passed_time":0.8836263536,"remaining_time":0.3715247168},
{"learn":[3.441904325],"iteration":704,"passed_time":0.8846877725,"remaining_time":0.3701885005},
{"learn":[3.438482051],"iteration":705,"passed_time":0.8858267124,"remaining_time":0.3688853448},
{"learn":[3.436543219],"iteration":706,"passed_time":0.8869121684,"remaining_time":0.3675604884},
{"learn":[3.434442032],"iteration":707,"passed_time":0.8880069457,"remaining_time":0.3662401527},
{"learn":[3.43296439],"iteration":708,"passed_time":0.8891232004,"remaining_time":0.3649292684},
{"learn":[3.432412967],"iteration":709,"passed_time":0.890204631,"remaining_time":0.3636047084},
{"learn":[3.430728004],"iteration":710,"passed_time":0.8913280752,"remaining_time":0.3622979096},
{"learn":[3.429024113],"iteration":711,"passed_time":0.8925172583,"remaining_time":0.3610182168},
{"learn":[3.428310728],"iteration":712,"passed_time":0.8936574008,"remaining_time":0.3597190379},
{"learn":[3.425233745],"iteration":713,"passed_time":0.8947624216,"remaining_time":0.3584062361},
{"learn":[3.423284523],"iteration":714,"passed_time":0.8958901072,"remaining_time":0.3571030497},
{"learn":[3.422132237],"iteration":715,"passed_time":0.8970697209,"remaining_time":0.3558209508},
{"learn":[3.419123347],"iteration":716,"passed_time":0.8982575269,"remaining_time":0.3545423712},
{"learn":[3.416591147],"iteration":717,"passed_time":0.8993191156,"remaining_time":0.3532144716},
{"learn":[3.414012474],"iteration":718,"passed_time":0.9004532249,"remaining_time":0.3519156553},
{"learn":[3.410916997],"iteration":719,"passed_time":0.9014476185,"remaining_time":0.3505629628},
{"learn":[3.408934728],"iteration":720,"passed_time":0.902530676,"remaining_time":0.3492455737},
{"learn":[3.406441193],"iteration":721,"passed_time":0.9036107682,"remaining_time":0.3479276919},
{"learn":[3.404068979],"iteration":722,"passed_time":0.9046685075,"remaining_time":0.346601904},
{"learn":[3.402146233],"iteration":723,"passed_time":0.9057328836,"remaining_time":0.3452793866},
{"learn":[3.399840526],"iteration":724,"passed_time":0.9069830411,"remaining_time":0.3440280501},
{"learn":[3.398669128],"iteration":725,"passed_time":0.9080483695,"remaining_time":0.3427069604},
{"learn":[3.397357914],"iteration":726,"passed_time":0.9091654214,"remaining_time":0.3414059973},
{"learn":[3.396501446],"iteration":727,"passed_time":0.9101899707,"remaining_time":0.3400709781},
{"learn":[3.39479046],"iteration":728,"passed_time":0.9113536934,"remaining_time":0.3387885472},
{"learn":[3.391265178],"iteration":729,"passed_time":0.9125743728,"remaining_time":0.3375275078},
{"learn":[3.387336747],"iteration":730,"passed_time":0.9136787371,"remaining_time":0.336223776},
{"learn":[3.385233866],"iteration":731,"passed_time":0.9148406441,"remaining_time":0.3349416566},
{"learn":[3.383736983],"iteration":732,"passed_time":0.9159618964,"remaining_time":0.3336450564},
{"learn":[3.3802625],"iteration":733,"passed_time":0.9170744372,"remaining_time":0.332345777},
{"learn":[3.379780191],"iteration":734,"passed_time":0.9180678095,"remaining_time":0.3310040401},
{"learn":[3.377556443],"iteration":735,"passed_time":0.9191032493,"remaining_time":0.3296783394},
{"learn":[3.376189703],"iteration":736,"passed_time":0.9202193347,"remaining_time":0.3283822049},
{"learn":[3.374425071],"iteration":737,"passed_time":0.921462347,"remaining_time":0.3271316191},
{"learn":[3.372375797],"iteration":738,"passed_time":0.9225683701,"remaining_time":0.325832672},
{"learn":[3.370286559],"iteration":739,"passed_time":0.923631816,"remaining_time":0.3245192867},
{"learn":[3.367291519],"iteration":740,"passed_time":0.9246901041,"remaining_time":0.3232047732},
{"learn":[3.365863908],"iteration":741,"passed_time":0.9258310033,"remaining_time":0.321919675},
{"learn":[3.362458053],"iteration":742,"passed_time":0.9268897678,"remaining_time":0.3206065549},
{"learn":[3.35964705],"iteration":743,"passed_time":0.9280430324,"remaining_time":0.3193266348},
{"learn":[3.35712418],"iteration":744,"passed_time":0.9292101005,"remaining_time":0.3180517794},
{"learn":[3.356624915],"iteration":745,"passed_time":0.9302650242,"remaining_time":0.3167390297},
{"learn":[3.355543825],"iteration":746,"passed_time":0.9313757125,"remaining_time":0.3154458571},
{"learn":[3.352843553],"iteration":747,"passed_time":0.9324556211,"remaining_time":0.3141428028},
{"learn":[3.350667054],"iteration":748,"passed_time":0.9335559448,"remaining_time":0.3128471858},
{"learn":[3.349185156],"iteration":749,"passed_time":0.9346185705,"remaining_time":0.3115395235},
{"learn":[3.346238171],"iteration":750,"passed_time":0.9360111663,"remaining_time":0.310341918},
{"learn":[3.343414367],"iteration":751,"passed_time":0.9370793837,"remaining_time":0.309036818},
{"learn":[3.342712884],"iteration":752,"passed_time":0.9381579796,"remaining_time":0.3077357516},
{"learn":[3.34154057],"iteration":753,"passed_time":0.9391996167,"remaining_time":0.3064232171},
{"learn":[3.339146406],"iteration":754,"passed_time":0.9402439721,"remaining_time":0.3051122823},
{"learn":[3.338347957],"iteration":755,"passed_time":0.9413631516,"remaining_time":0.3038262024},
{"learn":[3.337686305],"iteration":756,"passed_time":0.9424559606,"remaining_time":0.3025320983},
{"learn":[3.33615408],"iteration":757,"passed_time":0.9436262978,"remaining_time":0.3012632771},
{"learn":[3.335016575],"iteration":758,"passed_time":0.944718803,"remaining_time":0.299970002},
{"learn":[3.334030228],"iteration":759,"passed_time":0.9458508496,"remaining_time":0.298689742},
{"learn":[3.330890123],"iteration":760,"passed_time":0.9469617182,"remaining_time":0.2974032203},
{"learn":[3.329879265],"iteration":761,"passed_time":0.9480551284,"remaining_time":0.2961117068},
{"learn":[3.329456446],"iteration":762,"passed_time":0.9490897862,"remaining_time":0.2948024631},
{"learn":[3.329049616],"iteration":763,"passed_time":0.9506164545,"remaining_time":0.2936459205},
{"learn":[3.326517644],"iteration":764,"passed_time":0.9517412815,"remaining_time":0.2923649688},
{"learn":[3.324725053],"iteration":765,"passed_time":0.9528935348,"remaining_time":0.2910928031},
{"learn":[3.320909754],"iteration":766,"passed_time":0.9541657238,"remaining_time":0.2898573841},
{"learn":[3.32055837],"iteration":767,"passed_time":0.9554186101,"remaining_time":0.2886160385},
{"learn":[3.318512315],"iteration":768,"passed_time":0.956569822,"remaining_time":0.2873441208},
{"learn":[3.316540569],"iteration":769,"passed_time":0.9577125326,"remaining_time":0.2860699773},
{"learn":[3.314070397],"iteration":770,"passed_time":0.9591082778,"remaining_time":0.2848713302},
{"learn":[3.311765469],"iteration":771,"passed_time":0.9603460141,"remaining_time":0.2836255068},
{"learn":[3.308901754],"iteration":772,"passed_time":0.9614627652,"remaining_time":0.2823441756},
{"learn":[3.305418499],"iteration":773,"passed_time":0.9625695036,"remaining_time":0.281060346},
{"learn":[3.302416163],"iteration":774,"passed_time":0.96370217,"remaining_time":0.279784501},
{"learn":[3.300180973],"iteration":775,"passed_time":0.9648238238,"remaining_time":0.278505846},
{"learn":[3.299837149],"iteration":776,"passed_time":0.965879949,"remaining_time":0.2772087885},
{"learn":[3.296743855],"iteration":777,"passed_time":0.9670057731,"remaining_time":0.2759322386},
{"learn":[3.295551141],"iteration":778,"passed_time":0.9680414675,"remaining_time":0.2746305062},
{"learn":[3.294858738],"iteration":779,"passed_time":0.9691154964,"remaining_time":0.2733402682},
{"learn":[3.294272235],"iteration":780,"passed_time":0.9702193366,"remaining_time":0.2720589433},
{"learn":[3.2931692],"iteration":781,"passed_time":0.9712702188,"remaining_time":0.2707633091},
{"learn":[3.291478679],"iteration":782,"passed_time":0.9725122378,"remaining_time":0.2695212715},
{"learn":[3.290840008],"iteration":783,"passed_time":0.9737700655,"remaining_time":0.2682835895},
{"learn":[3.289686446],"iteration":784,"passed_time":0.9747835806,"remaining_time":0.2669789424},
{"learn":[3.288167014],"iteration":785,"passed_time":0.975871638,"remaining_time":0.2656953315},
{"learn":[3.285801752],"iteration":786,"passed_time":0.9769809345,"remaining_time":0.2644179658},
{"learn":[3.284002106],"iteration":787,"passed_time":0.9780946669,"remaining_time":0.26314222},
{"learn":[3.282248149],"iteration":788,"passed_time":0.9791782141,"remaining_time":0.2618588126},
{"learn":[3.280042315],"iteration":789,"passed_time":0.9803251947,"remaining_time":0.2605927733},
{"learn":[3.278360708],"iteration":790,"passed_time":0.9814102801,"remaining_time":0.2593106808},
{"learn":[3.276025974],"iteration":791,"passed_time":0.9825050374,"remaining_time":0.258031626},
{"learn":[3.273988829],"iteration":792,"passed_time":0.9835484015,"remaining_time":0.2567396206},
{"learn":[3.271766542],"iteration":793,"passed_time":0.9847171508,"remaining_time":0.2554807721},
{"learn":[3.270465525],"iteration":794,"passed_time":0.9857877161,"remaining_time":0.2541968325},
{"learn":[3.267444055],"iteration":795,"passed_time":0.9869636207,"remaining_time":0.2529404254},
{"learn":[3.266399634],"iteration":796,"passed_time":0.988114588,"remaining_time":0.2516778687},
{"learn":[3.264803768],"iteration":797,"passed_time":0.9892265032,"remaining_time":0.2504057063},
{"learn":[3.26334392],"iteration":798,"passed_time":0.9903282997,"remaining_time":0.2491313996},
{"learn":[3.262170608],"iteration":799,"passed_time":0.9913974179,"remaining_time":0.2478493545},
{"learn":[3.259873062],"iteration":800,"passed_time":0.9925026843,"remaining_time":0.2465768217},
{"learn":[3.259366333],"iteration":801,"passed_time":0.9936234159,"remaining_time":0.2453085241},
{"learn":[3.256806383],"iteration":802,"passed_time":0.9946937809,"remaining_time":0.2440282377},
{"learn":[3.256650554],"iteration":803,"passed_time":0.9957892491,"remaining_time":0.2427545931},
{"learn":[3.25602888],"iteration":804,"passed_time":0.9968684959,"remaining_time":0.2414774617},
{"learn":[3.254770211],"iteration":805,"passed_time":0.9979531898,"remaining_time":0.2402021325},
{"learn":[3.253022162],"iteration":806,"passed_time":0.9990659209,"remaining_time":0.2389339811},
{"learn":[3.249582148],"iteration":807,"passed_time":1.000100579,"remaining_time":0.2376476623},
{"learn":[3.249108031],"iteration":808,"passed_time":1.001157356,"remaining_time":0.2363671878},
{"learn":[3.248855702],"iteration":809,"passed_time":1.002318766,"remaining_time":0.2351118093},
{"learn":[3.247505228],"iteration":810,"passed_time":1.003434571,"remaining_time":0.2338460344},
{"learn":[3.245582649],"iteration":811,"passed_time":1.004499919,"remaining_time":0.2325689468},
{"learn":[3.242940893],"iteration":812,"passed_time":1.005779561,"remaining_time":0.2313416703},
{"learn":[3.242377365],"iteration":813,"passed_time":1.006897459,"remaining_time":0.2300773063},
{"learn":[3.241995931],"iteration":814,"passed_time":1.008053197,"remaining_time":0.2288218913},
{"learn":[3.240646294],"iteration":815,"passed_time":1.009185073,"remaining_time":0.22756134},
{"learn":[3.237836967],"iteration":816,"passed_time":1.010357893,"remaining_time":0.2263102746},
{"learn":[3.237458342],"iteration":817,"passed_time":1.011427817,"remaining_time":0.225036507},
{"learn":[3.23619697],"iteration":818,"passed_time":1.012495414,"remaining_time":0.2237627228},
{"learn":[3.235010079],"iteration":819,"passed_time":1.013574545,"remaining_time":0.2224919733},
{"learn":[3.23410911],"iteration":820,"passed_time":1.014631478,"remaining_time":0.2212168509},
{"learn":[3.233664657],"iteration":821,"passed_time":1.015679538,"remaining_time":0.2199403379},
{"learn":[3.233159255],"iteration":822,"passed_time":1.01671698,"remaining_time":0.2186620966},
{"learn":[3.23291781],"iteration":823,"passed_time":1.017830162,"remaining_time":0.2174006171},
{"learn":[3.232100477],"iteration":824,"passed_time":1.018904342,"remaining_time":0.2161312241},
{"learn":[3.229863388],"iteration":825,"passed_time":1.020066789,"remaining_time":0.2148808974},
{"learn":[3.228144236],"iteration":826,"passed_time":1.021232925,"remaining_time":0.2136315551},
{"learn":[3.22618706],"iteration":827,"passed_time":1.022343387,"remaining_time":0.2123708486},
{"learn":[3.225574432],"iteration":828,"passed_time":1.023395458,"remaining_time":0.21109846},
{"learn":[3.224226733],"iteration":829,"passed_time":1.024373457,"remaining_time":0.2098114309},
{"learn":[3.221951407],"iteration":830,"passed_time":1.025473797,"remaining_time":0.2085500261},
{"learn":[3.221259518],"iteration":831,"passed_time":1.026488078,"remaining_time":0.2072716311},
{"learn":[3.218521433],"iteration":832,"passed_time":1.027581543,"remaining_time":0.2060097452},
{"learn":[3.21572872],"iteration":833,"passed_time":1.028699862,"remaining_time":0.2047532099},
{"learn":[3.212023756],"iteration":834,"passed_time":1.029826932,"remaining_time":0.203498735},
{"learn":[3.208526027],"iteration":835,"passed_time":1.030955303,"remaining_time":0.2022448203},
{"learn":[3.207414387],"iteration":836,"passed_time":1.03201905,"remaining_time":0.2009786202},
{"learn":[3.205788629],"iteration":837,"passed_time":1.033138119,"remaining_time":0.1997235982},
{"learn":[3.204594032],"iteration":838,"passed_time":1.034241918,"remaining_time":0.19846597},
{"learn":[3.203383646],"iteration":839,"passed_time":1.035458436,"remaining_time":0.1972301782},
{"learn":[3.201619005],"iteration":840,"passed_time":1.036560993,"remaining_time":0.1959728869},
{"learn":[3.198657106],"iteration":841,"passed_time":1.037618186,"remaining_time":0.1947074507},
{"learn":[3.197494531],"iteration":842,"passed_time":1.038743274,"remaining_time":0.193455153},
{"learn":[3.197089474],"iteration":843,"passed_time":1.039821899,"remaining_time":0.192194569},
{"learn":[3.194720866],"iteration":844,"passed_time":1.040960315,"remaining_time":0.1909453832},
{"learn":[3.19234535],"iteration":845,"passed_time":1.042005236,"remaining_time":0.1896794402},
{"learn":[3.192202543],"iteration":846,"passed_time":1.043059595,"remaining_time":0.1884157237},
{"learn":[3.190249723],"iteration":847,"passed_time":1.044167504,"remaining_time":0.1871620997},
{"learn":[3.189255529],"iteration":848,"passed_time":1.045229658,"remaining_time":0.1859006812},
{"learn":[3.187446234],"iteration":849,"passed_time":1.046275036,"remaining_time":0.184636771},
{"learn":[3.18715315],"iteration":850,"passed_time":1.047447521,"remaining_time":0.1833956294},
{"learn":[3.185843536],"iteration":851,"passed_time":1.048626309,"remaining_time":0.1821557439},
{"learn":[3.184173912],"iteration":852,"passed_time":1.049703934,"remaining_time":0.1808985677},
{"learn":[3.181598548],"iteration":853,"passed_time":1.050823183,"remaining_time":0.1796489283},
{"learn":[3.179647423],"iteration":854,"passed_time":1.051873091,"remaining_time":0.1783878342},
{"learn":[3.176539333],"iteration":855,"passed_time":1.052983029,"remaining_time":0.1771373319},
{"learn":[3.175072704],"iteration":856,"passed_time":1.05415691,"remaining_time":0.1758978274},
{"learn":[3.174790111],"iteration":857,"passed_time":1.055277487,"remaining_time":0.174649654},
{"learn":[3.173422944],"iteration":858,"passed_time":1.056456614,"remaining_time":0.1734113883},
{"learn":[3.172091504],"iteration":859,"passed_time":1.057666293,"remaining_time":0.1721782337},
{"learn":[3.171214259],"iteration":860,"passed_time":1.058735476,"remaining_time":0.1709224521},
{"learn":[3.168479336],"iteration":861,"passed_time":1.059812958,"remaining_time":0.1696684318},
{"learn":[3.166021881],"iteration":862,"passed_time":1.06093027,"remaining_time":0.1684211436},
{"learn":[3.165640412],"iteration":863,"passed_time":1.062056719,"remaining_time":0.1671755947},
{"learn":[3.165079575],"iteration":864,"passed_time":1.06312035,"remaining_time":0.1659205171},
{"learn":[3.164093375],"iteration":865,"passed_time":1.064265775,"remaining_time":0.1646785379},
{"learn":[3.16354616],"iteration":866,"passed_time":1.06543085,"remaining_time":0.1634397958},
{"learn":[3.162244328],"iteration":867,"passed_time":1.066527149,"remaining_time":0.1621907646},
{"learn":[3.160942227],"iteration":868,"passed_time":1.067600333,"remaining_time":0.1609386002},
{"learn":[3.158743735],"iteration":869,"passed_time":1.06874782,"remaining_time":0.1596979501},
{"learn":[3.157878393],"iteration":870,"passed_time":1.069862714,"remaining_time":0.1584526867},
{"learn":[3.156800231],"iteration":871,"passed_time":1.070931637,"remaining_time":0.1572009742},
{"learn":[3.154890008],"iteration":872,"passed_time":1.072039536,"remaining_time":0.1559553506},
{"learn":[3.15204353],"iteration":873,"passed_time":1.073129507,"remaining_time":0.1547074576},
{"learn":[3.150442142],"iteration":874,"passed_time":1.07421702,"remaining_time":0.1534595743},
{"learn":[3.148862812],"iteration":875,"passed_time":1.075332964,"remaining_time":0.1522160817},
{"learn":[3.146897874],"iteration":876,"passed_time":1.076476758,"remaining_time":0.1509767858},
{"learn":[3.145528384],"iteration":877,"passed_time":1.077538266,"remaining_time":0.1497262738},
{"learn":[3.144255517],"iteration":878,"passed_time":1.07874771,"remaining_time":0.1484965562},
{"learn":[3.141822397],"iteration":879,"passed_time":1.079861062,"remaining_time":0.1472537811},
{"learn":[3.140542718],"iteration":880,"passed_time":1.081090617,"remaining_time":0.1460269959},
{"learn":[3.139476612],"iteration":881,"passed_time":1.082171296,"remaining_time":0.1447802867},
{"learn":[3.137559679],"iteration":882,"passed_time":1.083304458,"remaining_time":0.1435409079},
{"learn":[3.136720839],"iteration":883,"passed_time":1.084367018,"remaining_time":0.1422925047},
{"learn":[3.134915416],"iteration":884,"passed_time":1.085439075,"remaining_time":0.1410457555},
{"learn":[3.133583901],"iteration":885,"passed_time":1.086552973,"remaining_time":0.1398047843},
{"learn":[3.13191629],"iteration":886,"passed_time":1.087667641,"remaining_time":0.1385641978},
{"learn":[3.130310432],"iteration":887,"passed_time":1.088741991,"remaining_time":0.1373188097},
{"learn":[3.129347155],"iteration":888,"passed_time":1.089798243,"remaining_time":0.1360715467},
{"learn":[3.127536954],"iteration":889,"passed_time":1.091330933,"remaining_time":0.1348835985},
{"learn":[3.127241351],"iteration":890,"passed_time":1.092699655,"remaining_time":0.1336748175},
{"learn":[3.125757528],"iteration":891,"passed_time":1.093780334,"remaining_time":0.1324308027},
{"learn":[3.123725781],"iteration":892,"passed_time":1.094972219,"remaining_time":0.1312004787},
{"learn":[3.122106866],"iteration":893,"passed_time":1.096104095,"remaining_time":0.1299631253},
{"learn":[3.121033355],"iteration":894,"passed_time":1.097290949,"remaining_time":0.1287324577},
{"learn":[3.118382806],"iteration":895,"passed_time":1.098426495,"remaining_time":0.1274959325},
{"learn":[3.117839439],"iteration":896,"passed_time":1.099468573,"remaining_time":0.1262488997},
{"learn":[3.117487208],"iteration":897,"passed_time":1.100505142,"remaining_time":0.1250016977},
{"learn":[3.116678924],"iteration":898,"passed_time":1.101610785,"remaining_time":0.1237627244},
{"learn":[3.116537714],"iteration":899,"passed_time":1.102626848,"remaining_time":0.1225140942},
{"learn":[3.115717907],"iteration":900,"passed_time":1.103694394,"remaining_time":0.1212716371},
{"learn":[3.113983373],"iteration":901,"passed_time":1.10507901,"remaining_time":0.1200640166},
{"learn":[3.110669397],"iteration":902,"passed_time":1.106281019,"remaining_time":0.1188363885},
{"learn":[3.109959191],"iteration":903,"passed_time":1.107365027,"remaining_time":0.1175962861},
{"learn":[3.108658807],"iteration":904,"passed_time":1.108481708,"remaining_time":0.1163599583},
{"learn":[3.108171669],"iteration":905,"passed_time":1.109765405,"remaining_time":0.115141223},
{"learn":[3.10598098],"iteration":906,"passed_time":1.111033371,"remaining_time":0.1139207316},
{"learn":[3.10505712],"iteration":907,"passed_time":1.112292541,"remaining_time":0.1126992443},
{"learn":[3.102452534],"iteration":908,"passed_time":1.113417944,"remaining_time":0.1114642826},
{"learn":[3.100794499],"iteration":909,"passed_time":1.114507469,"remaining_time":0.1102260135},
{"learn":[3.09941495],"iteration":910,"passed_time":1.115740214,"remaining_time":0.1090020626},
{"learn":[3.096996321],"iteration":911,"passed_time":1.116868866,"remaining_time":0.1077680485},
{"learn":[3.096581439],"iteration":912,"passed_time":1.118004127,"remaining_time":0.1065348949},
{"learn":[3.094309064],"iteration":913,"passed_time":1.119173017,"remaining_time":0.1053051198},
{"learn":[3.093108587],"iteration":914,"passed_time":1.120324399,"remaining_time":0.1040738513},
{"learn":[3.090486975],"iteration":915,"passed_time":1.121439398,"remaining_time":0.1028394208},
{"learn":[3.088997841],"iteration":916,"passed_time":1.122575119,"remaining_time":0.1016071263},
{"learn":[3.086979308],"iteration":917,"passed_time":1.123770349,"remaining_time":0.1003803579},
{"learn":[3.086230764],"iteration":918,"passed_time":1.12486905,"remaining_time":0.09914515024},
{"learn":[3.084241656],"iteration":919,"passed_time":1.126009753,"remaining_time":0.09791389156},
{"learn":[3.082945302],"iteration":920,"passed_time":1.12711531,"remaining_time":0.09667981484},
{"learn":[3.082741262],"iteration":921,"passed_time":1.128219008,"remaining_time":0.09544585967},
{"learn":[3.079531719],"iteration":922,"passed_time":1.129335495,"remaining_time":0.09421325363},
{"learn":[3.078618241],"iteration":923,"passed_time":1.130381026,"remaining_time":0.09297506275},
{"learn":[3.075917406],"iteration":924,"passed_time":1.131496001,"remaining_time":0.091742919},
{"learn":[3.075231811],"iteration":925,"passed_time":1.132668061,"remaining_time":0.09051559015},
{"learn":[3.074421022],"iteration":926,"passed_time":1.133797043,"remaining_time":0.08928498829},
{"learn":[3.074183331],"iteration":927,"passed_time":1.134892912,"remaining_time":0.08805203626},
{"learn":[3.072321789],"iteration":928,"passed_time":1.136009888,"remaining_time":0.08682099255},
{"learn":[3.071068268],"iteration":929,"passed_time":1.137124982,"remaining_time":0.08559005238},
{"learn":[3.069343457],"iteration":930,"passed_time":1.138172788,"remaining_time":0.08435437417},
{"learn":[3.066772915],"iteration":931,"passed_time":1.139344947,"remaining_time":0.08312817212},
{"learn":[3.064459575],"iteration":932,"passed_time":1.140426697,"remaining_time":0.08189559349},
{"learn":[3.062805013],"iteration":933,"passed_time":1.141516157,"remaining_time":0.0806638826},
{"learn":[3.062047301],"iteration":934,"passed_time":1.14263763,"remaining_time":0.07943470157},
{"learn":[3.060954611],"iteration":935,"passed_time":1.143646043,"remaining_time":0.07819802006},
{"learn":[3.060081283],"iteration":936,"passed_time":1.144758594,"remaining_time":0.07696882757},
{"learn":[3.0597868],"iteration":937,"passed_time":1.146603333,"remaining_time":0.07578828},
{"learn":[3.058710045],"iteration":938,"passed_time":1.147585702,"remaining_time":0.07455029585},
{"learn":[3.058664671],"iteration":939,"passed_time":1.149011477,"remaining_time":0.07334115807},
{"learn":[3.057224235],"iteration":940,"passed_time":1.150076654,"remaining_time":0.07210895066},
{"learn":[3.054675322],"iteration":941,"passed_time":1.151226424,"remaining_time":0.07088230634},
{"learn":[3.052792905],"iteration":942,"passed_time":1.152334149,"remaining_time":0.06965328367},
{"learn":[3.051581484],"iteration":943,"passed_time":1.153425702,"remaining_time":0.0684235586},
{"learn":[3.049480067],"iteration":944,"passed_time":1.154665641,"remaining_time":0.06720276219},
{"learn":[3.047716873],"iteration":945,"passed_time":1.155803094,"remaining_time":0.06597607514},
{"learn":[3.045958712],"iteration":946,"passed_time":1.157207801,"remaining_time":0.06476453375},
{"learn":[3.045064537],"iteration":947,"passed_time":1.158373923,"remaining_time":0.06353949787},
{"learn":[3.043857342],"iteration":948,"passed_time":1.159736889,"remaining_time":0.06232516476},
{"learn":[3.0411782],"iteration":949,"passed_time":1.160853225,"remaining_time":0.06109753816},
{"learn":[3.039489009],"iteration":950,"passed_time":1.161996136,"remaining_time":0.0598715149},
{"learn":[3.037471824],"iteration":951,"passed_time":1.163101557,"remaining_time":0.058643776},
{"learn":[3.03643485],"iteration":952,"passed_time":1.164210197,"remaining_time":0.05741645254},
{"learn":[3.035461939],"iteration":953,"passed_time":1.165329162,"remaining_time":0.05618987575},
{"learn":[3.034167206],"iteration":954,"passed_time":1.166352635,"remaining_time":0.0549590247},
{"learn":[3.032571315],"iteration":955,"passed_time":1.167453361,"remaining_time":0.05373216306},
{"learn":[3.029572598],"iteration":956,"passed_time":1.168561936,"remaining_time":0.05250591773},
{"learn":[3.027393308],"iteration":957,"passed_time":1.169643797,"remaining_time":0.05127874683},
{"learn":[3.026978091],"iteration":958,"passed_time":1.170694866,"remaining_time":0.05005056258},
{"learn":[3.026816876],"iteration":959,"passed_time":1.171777943,"remaining_time":0.04882408095},
{"learn":[3.02454734],"iteration":960,"passed_time":1.172934282,"remaining_time":0.04760087095},
{"learn":[3.021620292],"iteration":961,"passed_time":1.173996201,"remaining_time":0.04637407029},
{"learn":[3.020713753],"iteration":962,"passed_time":1.17510431,"remaining_time":0.04514938679},
{"learn":[3.0179704],"iteration":963,"passed_time":1.176250355,"remaining_time":0.04392636182},
{"learn":[3.017202909],"iteration":964,"passed_time":1.177368433,"remaining_time":0.04270248204},
{"learn":[3.016783059],"iteration":965,"passed_time":1.178504591,"remaining_time":0.04147945764},
{"learn":[3.015443898],"iteration":966,"passed_time":1.179636737,"remaining_time":0.04025647604},
{"learn":[3.013567426],"iteration":967,"passed_time":1.180740386,"remaining_time":0.03903274005},
{"learn":[3.012217748],"iteration":968,"passed_time":1.181804693,"remaining_time":0.03780799329},
{"learn":[3.010862624],"iteration":969,"passed_time":1.182876065,"remaining_time":0.03658379581},
{"learn":[3.009924165],"iteration":970,"passed_time":1.184029499,"remaining_time":0.03536236404},
{"learn":[3.007805099],"iteration":971,"passed_time":1.185217933,"remaining_time":0.03414208038},
{"learn":[3.006165872],"iteration":972,"passed_time":1.186588272,"remaining_time":0.03292690991},
{"learn":[3.005244628],"iteration":973,"passed_time":1.187738232,"remaining_time":0.03170553803},
{"learn":[3.005024984],"iteration":974,"passed_time":1.188810129,"remaining_time":0.03048231101},
{"learn":[3.003796601],"iteration":975,"passed_time":1.189872296,"remaining_time":0.02925915483},
{"learn":[3.002978915],"iteration":976,"passed_time":1.190887686,"remaining_time":0.028035227},
{"learn":[3.002418098],"iteration":977,"passed_time":1.191979464,"remaining_time":0.02681344399},
{"learn":[3.001899255],"iteration":978,"passed_time":1.193016391,"remaining_time":0.02559074995},
{"learn":[2.999516239],"iteration":979,"passed_time":1.1940842,"remaining_time":0.0243690653},
{"learn":[2.999016543],"iteration":980,"passed_time":1.195234307,"remaining_time":0.02314928832},
{"learn":[2.99670704],"iteration":981,"passed_time":1.196328059,"remaining_time":0.02192862022},
{"learn":[2.995400318],"iteration":982,"passed_time":1.197526893,"remaining_time":0.02071002766},
{"learn":[2.994744034],"iteration":983,"passed_time":1.198619075,"remaining_time":0.01948974106},
{"learn":[2.992144528],"iteration":984,"passed_time":1.19982815,"remaining_time":0.01827149468},
{"learn":[2.989295334],"iteration":985,"passed_time":1.200868426,"remaining_time":0.01705087014},
{"learn":[2.987295413],"iteration":986,"passed_time":1.201881445,"remaining_time":0.01583025206},
{"learn":[2.984877167],"iteration":987,"passed_time":1.202975221,"remaining_time":0.01461103507},
{"learn":[2.981656306],"iteration":988,"passed_time":1.204138171,"remaining_time":0.01339284114},
{"learn":[2.97941189],"iteration":989,"passed_time":1.205190282,"remaining_time":0.01217363921},
{"learn":[2.977125658],"iteration":990,"passed_time":1.206302319,"remaining_time":0.01095531874},
{"learn":[2.975396181],"iteration":991,"passed_time":1.207315995,"remaining_time":0.009736419311},
{"learn":[2.973585853],"iteration":992,"passed_time":1.208413085,"remaining_time":0.008518521243},
{"learn":[2.971445608],"iteration":993,"passed_time":1.209479272,"remaining_time":0.007300679711},
{"learn":[2.971199703],"iteration":994,"passed_time":1.210558569,"remaining_time":0.006083208889},
{"learn":[2.969956833],"iteration":995,"passed_time":1.211558494,"remaining_time":0.004865696762},
{"learn":[2.967943865],"iteration":996,"passed_time":1.212584352,"remaining_time":0.003648699154},
{"learn":[2.965341896],"iteration":997,"passed_time":1.213877179,"remaining_time":0.002432619597},
{"learn":[2.964314304],"iteration":998,"passed_time":1.214924426,"remaining_time":0.001216140566},
{"learn":[2.963713941],"iteration":999,"passed_time":1.216035432,"remaining_time":0}
]}